rtl/math/fixed_point/shift/rtl/agr_fxp_shift.sv
`default_nettype none
`timescale 1ns/1ps

module agr_fxp_shift #(
    parameter int DATA_W   = 16,
    parameter int SHIFT_W  = 4,
    parameter bit USE_SATURATE = 1'b0
) (
    input  logic signed [DATA_W-1:0]  in_val,
    input  logic        [SHIFT_W-1:0] shift_amt,
    input  logic                      shift_dir,
    output logic signed [DATA_W-1:0]  out_val,
    output logic                      overflow,
    output logic                      precision_loss
);

    initial begin
        if (DATA_W < 1)  $fatal(1, "DATA_W must be >= 1");
        if (SHIFT_W < 1) $fatal(1, "SHIFT_W must be >= 1");
    end

    localparam int MAX_SHIFT = DATA_W;
    localparam int EFF_W = $clog2(MAX_SHIFT) + 1;

    localparam logic signed [DATA_W-1:0] SAT_MAX = {1'b0, {(DATA_W-1){1'b1}}};
    localparam logic signed [DATA_W-1:0] SAT_MIN = {1'b1, {(DATA_W-1){1'b0}}};

    // Effective shift (clamped)
    logic [EFF_W-1:0] effective_shift;
    assign effective_shift = (shift_amt >= MAX_SHIFT) ? MAX_SHIFT : shift_amt;

    // Full-width shift
    logic signed [2*DATA_W-1:0] shifted_full;
    assign shifted_full = shift_dir ? (in_val << effective_shift) : (in_val >>> effective_shift);

    // Truncated result
    logic signed [DATA_W-1:0] shifted_trunc;
    assign shifted_trunc = shifted_full[DATA_W-1:0];

    // Overflow: true if the truncated value != the full shifted value
    // This catches both sign-bit corruption AND magnitude overflow
    logic left_overflow;
    assign left_overflow = shift_dir && (effective_shift > 0) &&
                           (shifted_full !== signed'(shifted_trunc));

    // Precision loss: LSBs discarded in right shift
    logic [DATA_W-1:0] loss_mask;
    assign loss_mask = (1 << effective_shift) - 1;

    logic right_precision_loss;
    assign right_precision_loss = (!shift_dir) && (effective_shift > 0) &&
                                   |(in_val & loss_mask);

    assign overflow       = shift_dir ? left_overflow : 1'b0;
    assign precision_loss = shift_dir ? 1'b0 : right_precision_loss;

    // Saturation
    assign out_val = (USE_SATURATE && overflow) ? (in_val[DATA_W-1] ? SAT_MIN : SAT_MAX)
                                                  : shifted_trunc;

endmodule
`default_nettype wire

rtl/math/fixed_point/shift/tb/tb_agr_fxp_shift.sv
// =============================================================================
// tb_agr_fxp_shift : comprehensive self-checking testbench
// =============================================================================

`default_nettype none
`timescale 1ns/1ps

module tb_agr_fxp_shift;

    localparam int DATA_W = 8;
    localparam int SHIFT_W = 4;

    logic signed [DATA_W-1:0] in_val;
    logic [SHIFT_W-1:0] shift_amt;
    logic shift_dir;
    logic signed [DATA_W-1:0] out_wrap, out_sat;
    logic ovf_wrap, pl_wrap, ovf_sat, pl_sat;

    int errors = 0;
    int checks = 0;

    // Wrap instance
    agr_fxp_shift #(.DATA_W(DATA_W), .SHIFT_W(SHIFT_W), .USE_SATURATE(0))
        dut_wrap (.in_val, .shift_amt, .shift_dir, .out_val(out_wrap), .overflow(ovf_wrap), .precision_loss(pl_wrap));

    // Saturate instance
    agr_fxp_shift #(.DATA_W(DATA_W), .SHIFT_W(SHIFT_W), .USE_SATURATE(1))
        dut_sat  (.in_val, .shift_amt, .shift_dir, .out_val(out_sat), .overflow(ovf_sat), .precision_loss(pl_sat));

    // -------------------------------------------------------------------
    // Golden model (64-bit)
    // -------------------------------------------------------------------
    task automatic golden_shift(
        input longint in64,
        input int amt,
        input bit dir,
        input bit sat,
        output longint exp_out,
        output bit exp_ovf,
        output bit exp_pl
    );
        longint shifted, max_val, min_val;
        longint loss_mask;

        max_val = (1 << (DATA_W - 1)) - 1;
        min_val = -(1 << (DATA_W - 1));

        if (dir) begin
            // Left shift
            shifted = in64 << amt;
            exp_pl = 0;
            // Overflow: check if shifted value exceeds DATA_W signed range
            exp_ovf = (shifted > max_val) || (shifted < min_val);
            if (sat && exp_ovf)
                exp_out = (in64 < 0) ? min_val : max_val;
            else
                exp_out = shifted & ((1 << DATA_W) - 1);
            // Sign-extend if needed
            if (exp_out >= (1 << (DATA_W - 1)))
                exp_out = exp_out - (1 << DATA_W);
        end else begin
            // Right shift: arithmetic
            shifted = in64 >>> amt;
            exp_ovf = 0;
            loss_mask = (1 << amt) - 1;
            exp_pl = ((in64 & loss_mask) != 0);
            exp_out = shifted & ((1 << DATA_W) - 1);
            if (exp_out >= (1 << (DATA_W - 1)))
                exp_out = exp_out - (1 << DATA_W);
        end
    endtask

    // -------------------------------------------------------------------
    // Check
    // -------------------------------------------------------------------
    task automatic check;
        input string label;
        input longint in64;
        input int amt;
        input bit dir;
        longint exp_wrap, exp_sat;
        bit exp_ovf, exp_pl;
        begin
            golden_shift(in64, amt, dir, 0, exp_wrap, exp_ovf, exp_pl);
            checks = checks + 1;
            if (out_wrap !== exp_wrap || ovf_wrap !== exp_ovf || pl_wrap !== exp_pl) begin
                errors = errors + 1;
                $error("[%s] WRAP in=%0d amt=%0d dir=%0d | exp out=%0d ovf=%0b pl=%0b | got out=%0d ovf=%0b pl=%0b",
                       label, in64, amt, dir, exp_wrap, exp_ovf, exp_pl, out_wrap, ovf_wrap, pl_wrap);
            end
            golden_shift(in64, amt, dir, 1, exp_sat, exp_ovf, exp_pl);
            checks = checks + 1;
            if (out_sat !== exp_sat || ovf_sat !== exp_ovf || pl_sat !== exp_pl) begin
                errors = errors + 1;
                $error("[%s] SAT  in=%0d amt=%0d dir=%0d | exp out=%0d ovf=%0b pl=%0b | got out=%0d ovf=%0b pl=%0b",
                       label, in64, amt, dir, exp_sat, exp_ovf, exp_pl, out_sat, ovf_sat, pl_sat);
            end
        end
    endtask

    task automatic drive;
        input longint in64;
        input int amt;
        input bit dir;
        begin
            in_val = in64[DATA_W-1:0];
            shift_amt = amt[SHIFT_W-1:0];
            shift_dir = dir;
            #1;
            check("", in64, amt, dir);
        end
    endtask

    // ===================================================================
    // TEST 1: Shift by zero (passthrough)
    // ===================================================================
    task automatic test_shift_zero();
        $display("--- Test 1: Shift by zero ---");
        drive(0, 0, 0); drive(0, 0, 1);
        drive(1, 0, 0); drive(1, 0, 1);
        drive(-1, 0, 0); drive(-1, 0, 1);
        drive(127, 0, 0); drive(127, 0, 1);
        drive(-128, 0, 0); drive(-128, 0, 1);
        $display("  done (%0d checks)", checks);
    endtask

    // ===================================================================
    // TEST 2: Left shift - no overflow
    // ===================================================================
    task automatic test_left_no_overflow();
        $display("--- Test 2: Left shift, no overflow ---");
        drive(1, 1, 1);    // 1<<1=2
        drive(1, 4, 1);    // 1<<4=16
        drive(3, 2, 1);    // 3<<2=12
        drive(-1, 3, 1);   // -1<<3=-8 (sign-extended correctly)
        drive(-4, 2, 1);   // -4<<2=-16
        drive(15, 3, 1);   // 15<<3=120 (just fits)
        drive(-16, 3, 1);  // -16<<3=-128 (just fits - MIN)
        $display("  done (%0d checks)", checks);
    endtask

    // ===================================================================
    // TEST 3: Left shift - overflow
    // ===================================================================
    task automatic test_left_overflow();
        $display("--- Test 3: Left shift, overflow ---");
        drive(16, 3, 1);    // 16<<3=128 > 127 -> overflow
        drive(-17, 3, 1);   // -17<<3=-136 < -128 -> overflow
        drive(64, 2, 1);    // 64<<2=256 > 127 -> overflow, wrap to 0
        drive(-64, 2, 1);   // -64<<2=-256 < -128 -> overflow, wrap to 0
        drive(127, 1, 1);   // 127<<1=254 > 127 -> overflow
        drive(-128, 1, 1);  // -128<<1=-256 < -128 -> overflow
        drive(1, 7, 1);     // 1<<7=128 -> overflow (just past MAX)
        drive(-1, 7, 1);    // -1<<7=-128 -> no overflow (exact MIN)
        $display("  done (%0d checks)", checks);
    endtask

    // ===================================================================
    // TEST 4: Right shift - arithmetic
    // ===================================================================
    task automatic test_right_arithmetic();
        $display("--- Test 4: Right shift, arithmetic ---");
        drive(16, 1, 0);    // 16>>1=8, pl=0
        drive(17, 1, 0);    // 17>>1=8, pl=1 (LSB 1 lost)
        drive(-16, 1, 0);   // -16>>1=-8, pl=0
        drive(-17, 1, 0);   // -17>>1=-9, pl=1
        drive(127, 4, 0);   // 127>>4=7, pl=1
        drive(-128, 4, 0);  // -128>>4=-8, pl=0
        drive(-1, 4, 0);    // -1>>4=-1 (sign-extended), pl=1
        drive(0, 5, 0);     // 0>>5=0, pl=0
        $display("  done (%0d checks)", checks);
    endtask

    // ===================================================================
    // TEST 5: Shift >= DATA_W (extreme)
    // ===================================================================
    task automatic test_extreme_shifts();
        $display("--- Test 5: Extreme shifts (>= DATA_W) ---");
        // Left shift by DATA_W: everything shifted out
        drive(1, 8, 1);      // all bits shifted out -> overflow
        drive(-1, 8, 1);     // -1, all 1s -> overflow
        drive(0, 8, 1);      // 0 -> ok
        // Left shift beyond DATA_W (clamped)
        drive(1, 15, 1);     // shift_amt=15, clamped to 8 -> overflow
        // Right shift by DATA_W: all bits shifted out, result is sign
        drive(127, 8, 0);    // 127>>8=0, pl=1 (all bits lost)
        drive(-128, 8, 0);   // -128>>8=-1 (sign-extended to all 1s), pl=0
        drive(-1, 8, 0);     // -1>>8=-1, pl=1
        drive(85, 15, 0);    // clamped to 8, 85>>8=0, pl=1
        $display("  done (%0d checks)", checks);
    endtask

    // ===================================================================
    // TEST 6: Saturation behavior
    // ===================================================================
    task automatic test_saturation();
        $display("--- Test 6: Saturation ---");
        drive(64, 2, 1);     // 256 > 127 -> sat to 127
        drive(-64, 2, 1);    // -256 < -128 -> sat to -128
        drive(1, 7, 1);      // 128 -> sat to 127
        drive(-2, 7, 1);     // -256 -> sat to -128
        drive(127, 1, 1);    // 254 -> sat to 127
        drive(-128, 1, 1);   // -256 -> sat to -128
        $display("  done (%0d checks)", checks);
    endtask

    // ===================================================================
    // TEST 7: Precision loss (right shift)
    // ===================================================================
    task automatic test_precision_loss();
        $display("--- Test 7: Precision loss ---");
        drive(3, 1, 0);      // 3>>1=1, pl=1 (bit 0 lost)
        drive(2, 1, 0);      // 2>>1=1, pl=0
        drive(5, 2, 0);      // 5>>2=1, pl=1 (bits 0,1 lost)
        drive(4, 2, 0);      // 4>>2=1, pl=0
        drive(-3, 1, 0);     // -3>>1=-2, pl=1
        drive(-4, 1, 0);     // -4>>1=-2, pl=0
        $display("  done (%0d checks)", checks);
    endtask

    // ===================================================================
    // TEST 8: Random regression
    // ===================================================================
    task automatic test_random();
        longint v;
        int amt;
        bit dir;
        integer i;
        $display("--- Test 8: Random (3000 cases) ---");
        for (i = 0; i < 3000; i = i + 1) begin
            v   = (($urandom() & 32'h7FFFFFFF) % 256) - 128;
            amt = ($urandom() & 32'h7FFFFFFF) % 16;
            dir = ($urandom() & 1);
            drive(v, amt, dir);
        end
        $display("  done (%0d checks)", checks);
    endtask

    // ===================================================================
    // Main
    // ===================================================================
    initial begin
        $display("=== agr_fxp_shift comprehensive testbench ===");
        $display("DATA_W=%0d, SHIFT_W=%0d", DATA_W, SHIFT_W);

        test_shift_zero();
        test_left_no_overflow();
        test_left_overflow();
        test_right_arithmetic();
        test_extreme_shifts();
        test_saturation();
        test_precision_loss();
        test_random();

        $display("");
        $display("=== %0d checks run, %0d errors ===", checks, errors);
        if (errors == 0) begin
            $display("*** ALL TESTS PASSED ***");
            $finish;
        end else begin
            $display("*** TEST FAILED: %0d errors ***", errors);
            $stop;
        end
    end

endmodule
`default_nettype wire

rtl/math/fixed_point/shift/sim/wave.vcd
$version Generated by VerilatedVcd $end
$timescale 1ps $end
 $scope module TOP $end
  $scope module tb_agr_fxp_shift $end
   $var wire 32 . DATA_W [31:0] $end
   $var wire 32 / SHIFT_W [31:0] $end
   $var wire 8 " in_val [7:0] $end
   $var wire 4 # shift_amt [3:0] $end
   $var wire 1 $ shift_dir $end
   $var wire 8 ' out_wrap [7:0] $end
   $var wire 8 ( out_sat [7:0] $end
   $var wire 1 ) ovf_wrap $end
   $var wire 1 * pl_wrap $end
   $var wire 1 ) ovf_sat $end
   $var wire 1 * pl_sat $end
   $var wire 32 % errors [31:0] $end
   $var wire 32 & checks [31:0] $end
   $scope module dut_sat $end
    $var wire 32 . DATA_W [31:0] $end
    $var wire 32 / SHIFT_W [31:0] $end
    $var wire 1 0 USE_SATURATE $end
    $var wire 8 " in_val [7:0] $end
    $var wire 4 # shift_amt [3:0] $end
    $var wire 1 $ shift_dir $end
    $var wire 8 ( out_val [7:0] $end
    $var wire 1 ) overflow $end
    $var wire 1 * precision_loss $end
    $var wire 32 . MAX_SHIFT [31:0] $end
    $var wire 32 / EFF_W [31:0] $end
    $var wire 8 1 SAT_MAX [7:0] $end
    $var wire 8 2 SAT_MIN [7:0] $end
    $var wire 4 + effective_shift [3:0] $end
    $var wire 16 , shifted_full [15:0] $end
    $var wire 8 ' shifted_trunc [7:0] $end
    $var wire 1 ) left_overflow $end
    $var wire 8 - loss_mask [7:0] $end
    $var wire 1 * right_precision_loss $end
   $upscope $end
   $scope module dut_wrap $end
    $var wire 32 . DATA_W [31:0] $end
    $var wire 32 / SHIFT_W [31:0] $end
    $var wire 1 3 USE_SATURATE $end
    $var wire 8 " in_val [7:0] $end
    $var wire 4 # shift_amt [3:0] $end
    $var wire 1 $ shift_dir $end
    $var wire 8 ' out_val [7:0] $end
    $var wire 1 ) overflow $end
    $var wire 1 * precision_loss $end
    $var wire 32 . MAX_SHIFT [31:0] $end
    $var wire 32 / EFF_W [31:0] $end
    $var wire 8 1 SAT_MAX [7:0] $end
    $var wire 8 2 SAT_MIN [7:0] $end
    $var wire 4 + effective_shift [3:0] $end
    $var wire 16 , shifted_full [15:0] $end
    $var wire 8 ' shifted_trunc [7:0] $end
    $var wire 1 ) left_overflow $end
    $var wire 8 - loss_mask [7:0] $end
    $var wire 1 * right_precision_loss $end
   $upscope $end
  $upscope $end
 $upscope $end
$enddefinitions $end


#0
b00000000 "
b0000 #
0$
b00000000000000000000000000000000 %
b00000000000000000000000000000000 &
b00000000 '
b00000000 (
0)
0*
b0000 +
b0000000000000000 ,
b00000000 -
b00000000000000000000000000001000 .
b00000000000000000000000000000100 /
10
b01111111 1
b10000000 2
03
#1000
1$
b00000000000000000000000000000010 &
#2000
b00000001 "
0$
b00000000000000000000000000000100 &
b00000001 '
b00000001 (
b0000000000000001 ,
#3000
1$
b00000000000000000000000000000110 &
#4000
b11111111 "
0$
b00000000000000000000000000001000 &
b11111111 '
b11111111 (
b1111111111111111 ,
#5000
1$
b00000000000000000000000000001010 &
#6000
b01111111 "
0$
b00000000000000000000000000001100 &
b01111111 '
b01111111 (
b0000000001111111 ,
#7000
1$
b00000000000000000000000000001110 &
#8000
b10000000 "
0$
b00000000000000000000000000010000 &
b10000000 '
b10000000 (
b1111111110000000 ,
#9000
1$
b00000000000000000000000000010010 &
#10000
b00000001 "
b0001 #
b00000000000000000000000000010100 &
b00000010 '
b00000010 (
b0001 +
b0000000000000010 ,
b00000001 -
#11000
b0100 #
b00000000000000000000000000010110 &
b00010000 '
b00010000 (
b0100 +
b0000000000010000 ,
b00001111 -
#12000
b00000011 "
b0010 #
b00000000000000000000000000011000 &
b00001100 '
b00001100 (
b0010 +
b0000000000001100 ,
b00000011 -
#13000
b11111111 "
b0011 #
b00000000000000000000000000011010 &
b11111000 '
b11111000 (
b0011 +
b1111111111111000 ,
b00000111 -
#14000
b11111100 "
b0010 #
b00000000000000000000000000011100 &
b11110000 '
b11110000 (
b0010 +
b1111111111110000 ,
b00000011 -
#15000
b00001111 "
b0011 #
b00000000000000000000000000011110 &
b01111000 '
b01111000 (
b0011 +
b0000000001111000 ,
b00000111 -
#16000
b11110000 "
b00000000000000000000000000100000 &
b10000000 '
b10000000 (
b1111111110000000 ,
#17000
b00010000 "
b00000000000000000000000000100010 &
b01111111 (
1)
b0000000010000000 ,
#18000
b11101111 "
b00000000000000000000000000100100 &
b01111000 '
b10000000 (
b1111111101111000 ,
#19000
b01000000 "
b0010 #
b00000000000000000000000000100110 &
b00000000 '
b01111111 (
b0010 +
b0000000100000000 ,
b00000011 -
#20000
b11000000 "
b00000000000000000000000000101000 &
b10000000 (
b1111111100000000 ,
#21000
b01111111 "
b0001 #
b00000000000000000000000000101010 &
b11111110 '
b01111111 (
b0001 +
b0000000011111110 ,
b00000001 -
#22000
b10000000 "
b00000000000000000000000000101100 &
b00000000 '
b10000000 (
b1111111100000000 ,
#23000
b00000001 "
b0111 #
b00000000000000000000000000101110 &
b10000000 '
b01111111 (
b0111 +
b0000000010000000 ,
b01111111 -
#24000
b11111111 "
b00000000000000000000000000110000 &
b10000000 (
0)
b1111111110000000 ,
#25000
b00010000 "
b0001 #
0$
b00000000000000000000000000110010 &
b00001000 '
b00001000 (
b0001 +
b0000000000001000 ,
b00000001 -
#26000
b00010001 "
b00000000000000000000000000110100 &
1*
#27000
b11110000 "
b00000000000000000000000000110110 &
b11111000 '
b11111000 (
0*
b1111111111111000 ,
#28000
b11101111 "
b00000000000000000000000000111000 &
b11110111 '
b11110111 (
1*
b1111111111110111 ,
#29000
b01111111 "
b0100 #
b00000000000000000000000000111010 &
b00000111 '
b00000111 (
b0100 +
b0000000000000111 ,
b00001111 -
#30000
b10000000 "
b00000000000000000000000000111100 &
b11111000 '
b11111000 (
0*
b1111111111111000 ,
#31000
b11111111 "
b00000000000000000000000000111110 &
b11111111 '
b11111111 (
1*
b1111111111111111 ,
#32000
b00000000 "
b0101 #
b00000000000000000000000001000000 &
b00000000 '
b00000000 (
0*
b0101 +
b0000000000000000 ,
b00011111 -
#33000
b00000001 "
b1000 #
1$
b00000000000000000000000001000010 &
b01111111 (
1)
b1000 +
b0000000100000000 ,
b11111111 -
#34000
b11111111 "
b00000000000000000000000001000100 &
b10000000 (
b1111111100000000 ,
#35000
b00000000 "
b00000000000000000000000001000110 &
b00000000 (
0)
b0000000000000000 ,
#36000
b00000001 "
b1111 #
b00000000000000000000000001001000 &
b01111111 (
1)
b0000000100000000 ,
#37000
b01111111 "
b1000 #
0$
b00000000000000000000000001001010 &
b00000000 (
0)
1*
b0000000000000000 ,
#38000
b10000000 "
b00000000000000000000000001001100 &
b11111111 '
b11111111 (
b1111111111111111 ,
#39000
b11111111 "
b00000000000000000000000001001110 &
#40000
b01010101 "
b1111 #
b00000000000000000000000001010000 &
b00000000 '
b00000000 (
b0000000000000000 ,
#41000
b01000000 "
b0010 #
1$
b00000000000000000000000001010010 &
b01111111 (
1)
0*
b0010 +
b0000000100000000 ,
b00000011 -
#42000
b11000000 "
b00000000000000000000000001010100 &
b10000000 (
b1111111100000000 ,
#43000
b00000001 "
b0111 #
b00000000000000000000000001010110 &
b10000000 '
b01111111 (
b0111 +
b0000000010000000 ,
b01111111 -
#44000
b11111110 "
b00000000000000000000000001011000 &
b00000000 '
b10000000 (
b1111111100000000 ,
#45000
b01111111 "
b0001 #
b00000000000000000000000001011010 &
b11111110 '
b01111111 (
b0001 +
b0000000011111110 ,
b00000001 -
#46000
b10000000 "
b00000000000000000000000001011100 &
b00000000 '
b10000000 (
b1111111100000000 ,
#47000
b00000011 "
0$
b00000000000000000000000001011110 &
b00000001 '
b00000001 (
0)
1*
b0000000000000001 ,
#48000
b00000010 "
b00000000000000000000000001100000 &
0*
#49000
b00000101 "
b0010 #
b00000000000000000000000001100010 &
1*
b0010 +
b00000011 -
#50000
b00000100 "
b00000000000000000000000001100100 &
0*
#51000
b11111101 "
b0001 #
b00000000000000000000000001100110 &
b11111110 '
b11111110 (
1*
b0001 +
b1111111111111110 ,
b00000001 -
#52000
b11111100 "
b00000000000000000000000001101000 &
0*
#53000
b10010010 "
b0111 #
1$
b00000000000000000000000001101010 &
b00000000 '
b10000000 (
1)
b0111 +
b1100100100000000 ,
b01111111 -
#54000
b11110010 "
b1110 #
b00000000000000000000000001101100 &
b1000 +
b1111001000000000 ,
b11111111 -
#55000
b11001011 "
b0111 #
b00000000000000000000000001101110 &
b10000000 '
b0111 +
b1110010110000000 ,
b01111111 -
#56000
b01011000 "
b1110 #
b00000000000000000000000001110000 &
b00000000 '
b01111111 (
b1000 +
b0101100000000000 ,
b11111111 -
#57000
b00000101 "
b0000 #
b00000000000000000000000001110010 &
b00000101 '
b00000101 (
0)
b0000 +
b0000000000000101 ,
b00000000 -
#58000
b11001010 "
b0100 #
b00000000000000000000000001110100 &
b10100000 '
b10000000 (
1)
b0100 +
b1111110010100000 ,
b00001111 -
#59000
b00011101 "
b1011 #
b00000000000000000000000001110110 &
b00000000 '
b01111111 (
b1000 +
b0001110100000000 ,
b11111111 -
#60000
b01101111 "
b00000000000000000000000001111000 &
b0110111100000000 ,
#61000
b01100100 "
0$
b00000000000000000000000001111010 &
b00000000 (
0)
1*
b0000000000000000 ,
#62000
b11101011 "
b0011 #
1$
b00000000000000000000000001111100 &
b01011000 '
b10000000 (
1)
0*
b0011 +
b1111111101011000 ,
b00000111 -
#63000
b00100011 "
b1011 #
b00000000000000000000000001111110 &
b00000000 '
b01111111 (
b1000 +
b0010001100000000 ,
b11111111 -
#64000
b10010001 "
b1101 #
b00000000000000000000000010000000 &
b10000000 (
b1001000100000000 ,
#65000
b00011110 "
b0010 #
0$
b00000000000000000000000010000010 &
b00000111 '
b00000111 (
0)
1*
b0010 +
b0000000000000111 ,
b00000011 -
#66000
b11000101 "
b1010 #
b00000000000000000000000010000100 &
b11111111 '
b11111111 (
b1000 +
b1111111111111111 ,
b11111111 -
#67000
b10010100 "
b1110 #
b00000000000000000000000010000110 &
#68000
b00110010 "
b0101 #
b00000000000000000000000010001000 &
b00000001 '
b00000001 (
b0101 +
b0000000000000001 ,
b00011111 -
#69000
b00011010 "
b1111 #
b00000000000000000000000010001010 &
b00000000 '
b00000000 (
b1000 +
b0000000000000000 ,
b11111111 -
#70000
b11101000 "
b1110 #
1$
b00000000000000000000000010001100 &
b10000000 (
1)
0*
b1110100000000000 ,
#71000
b11010101 "
b0101 #
0$
b00000000000000000000000010001110 &
b11111110 '
b11111110 (
0)
1*
b0101 +
b1111111111111110 ,
b00011111 -
#72000
b00110001 "
b0111 #
b00000000000000000000000010010000 &
b00000000 '
b00000000 (
b0111 +
b0000000000000000 ,
b01111111 -
#73000
b00000101 "
b1000 #
1$
b00000000000000000000000010010010 &
b01111111 (
1)
0*
b1000 +
b0000010100000000 ,
b11111111 -
#74000
b00000011 "
b0000 #
0$
b00000000000000000000000010010100 &
b00000011 '
b00000011 (
0)
b0000 +
b0000000000000011 ,
b00000000 -
#75000
b00110000 "
b1010 #
b00000000000000000000000010010110 &
b00000000 '
b00000000 (
1*
b1000 +
b0000000000000000 ,
b11111111 -
#76000
b01010100 "
b1111 #
b00000000000000000000000010011000 &
#77000
b00101011 "
b0010 #
b00000000000000000000000010011010 &
b00001010 '
b00001010 (
b0010 +
b0000000000001010 ,
b00000011 -
#78000
b00110010 "
b0110 #
b00000000000000000000000010011100 &
b00000000 '
b00000000 (
b0110 +
b0000000000000000 ,
b00111111 -
#79000
b10011101 "
b0010 #
b00000000000000000000000010011110 &
b11100111 '
b11100111 (
b0010 +
b1111111111100111 ,
b00000011 -
#80000
b01100101 "
b1010 #
1$
b00000000000000000000000010100000 &
b00000000 '
b01111111 (
1)
0*
b1000 +
b0110010100000000 ,
b11111111 -
#81000
b11011110 "
b1100 #
b00000000000000000000000010100010 &
b10000000 (
b1101111000000000 ,
#82000
b01111001 "
b1111 #
b00000000000000000000000010100100 &
b01111111 (
b0111100100000000 ,
#83000
b01100111 "
b1110 #
b00000000000000000000000010100110 &
b0110011100000000 ,
#84000
b01111010 "
b0011 #
0$
b00000000000000000000000010101000 &
b00001111 '
b00001111 (
0)
1*
b0011 +
b0000000000001111 ,
b00000111 -
#85000
b10000110 "
b00000000000000000000000010101010 &
b11110000 '
b11110000 (
b1111111111110000 ,
#86000
b11100110 "
b1110 #
b00000000000000000000000010101100 &
b11111111 '
b11111111 (
b1000 +
b1111111111111111 ,
b11111111 -
#87000
b00100000 "
b1100 #
1$
b00000000000000000000000010101110 &
b00000000 '
b01111111 (
1)
0*
b0010000000000000 ,
#88000
b10011101 "
b1110 #
b00000000000000000000000010110000 &
b10000000 (
b1001110100000000 ,
#89000
b11101100 "
0$
b00000000000000000000000010110010 &
b11111111 '
b11111111 (
0)
1*
b1111111111111111 ,
#90000
b10000110 "
b1000 #
1$
b00000000000000000000000010110100 &
b00000000 '
b10000000 (
1)
0*
b1000011000000000 ,
#91000
b01111010 "
0$
b00000000000000000000000010110110 &
b00000000 (
0)
1*
b0000000000000000 ,
#92000
b10010000 "
b0011 #
1$
b00000000000000000000000010111000 &
b10000000 '
b10000000 (
1)
0*
b0011 +
b1111110010000000 ,
b00000111 -
#93000
b11111110 "
b1000 #
0$
b00000000000000000000000010111010 &
b11111111 '
b11111111 (
0)
1*
b1000 +
b1111111111111111 ,
b11111111 -
#94000
b10011100 "
b1001 #
b00000000000000000000000010111100 &
#95000
b11101100 "
b1011 #
1$
b00000000000000000000000010111110 &
b00000000 '
b10000000 (
1)
0*
b1110110000000000 ,
#96000
b10110101 "
b1001 #
b00000000000000000000000011000000 &
b1011010100000000 ,
#97000
b01000100 "
b1011 #
b00000000000000000000000011000010 &
b01111111 (
b0100010000000000 ,
#98000
b11011001 "
b0011 #
0$
b00000000000000000000000011000100 &
b11111011 '
b11111011 (
0)
1*
b0011 +
b1111111111111011 ,
b00000111 -
#99000
b01011000 "
b0111 #
1$
b00000000000000000000000011000110 &
b00000000 '
b01111111 (
1)
0*
b0111 +
b0010110000000000 ,
b01111111 -
#100000
b10100010 "
b1000 #
b00000000000000000000000011001000 &
b10000000 (
b1000 +
b1010001000000000 ,
b11111111 -
#101000
b01000100 "
b0111 #
b00000000000000000000000011001010 &
b01111111 (
b0111 +
b0010001000000000 ,
b01111111 -
#102000
b00110011 "
b0000 #
b00000000000000000000000011001100 &
b00110011 '
b00110011 (
0)
b0000 +
b0000000000110011 ,
b00000000 -
#103000
b10100101 "
b1101 #
0$
b00000000000000000000000011001110 &
b11111111 '
b11111111 (
1*
b1000 +
b1111111111111111 ,
b11111111 -
#104000
b00110110 "
b0110 #
b00000000000000000000000011010000 &
b00000000 '
b00000000 (
b0110 +
b0000000000000000 ,
b00111111 -
#105000
b00101110 "
b0000 #
1$
b00000000000000000000000011010010 &
b00101110 '
b00101110 (
0*
b0000 +
b0000000000101110 ,
b00000000 -
#106000
b00011110 "
b1111 #
0$
b00000000000000000000000011010100 &
b00000000 '
b00000000 (
1*
b1000 +
b0000000000000000 ,
b11111111 -
#107000
b00101101 "
b0100 #
1$
b00000000000000000000000011010110 &
b11010000 '
b01111111 (
1)
0*
b0100 +
b0000001011010000 ,
b00001111 -
#108000
b11011011 "
b1110 #
b00000000000000000000000011011000 &
b00000000 '
b10000000 (
b1000 +
b1101101100000000 ,
b11111111 -
#109000
b01010011 "
b0001 #
0$
b00000000000000000000000011011010 &
b00101001 '
b00101001 (
0)
1*
b0001 +
b0000000000101001 ,
b00000001 -
#110000
b01111111 "
b1101 #
b00000000000000000000000011011100 &
b00000000 '
b00000000 (
b1000 +
b0000000000000000 ,
b11111111 -
#111000
b01000111 "
b1111 #
1$
b00000000000000000000000011011110 &
b01111111 (
1)
0*
b0100011100000000 ,
#112000
b00101111 "
b1000 #
b00000000000000000000000011100000 &
b0010111100000000 ,
#113000
b10000001 "
b00000000000000000000000011100010 &
b10000000 (
b1000000100000000 ,
#114000
b01100100 "
b1110 #
b00000000000000000000000011100100 &
b01111111 (
b0110010000000000 ,
#115000
b00101111 "
b0110 #
b00000000000000000000000011100110 &
b11000000 '
b0110 +
b0000101111000000 ,
b00111111 -
#116000
b11100011 "
b0101 #
b00000000000000000000000011101000 &
b01100000 '
b10000000 (
b0101 +
b1111110001100000 ,
b00011111 -
#117000
b01101011 "
b0011 #
b00000000000000000000000011101010 &
b01011000 '
b01111111 (
b0011 +
b0000001101011000 ,
b00000111 -
#118000
b11110110 "
b0101 #
b00000000000000000000000011101100 &
b11000000 '
b10000000 (
b0101 +
b1111111011000000 ,
b00011111 -
#119000
b00011100 "
b0010 #
0$
b00000000000000000000000011101110 &
b00000111 '
b00000111 (
0)
b0010 +
b0000000000000111 ,
b00000011 -
#120000
b01110001 "
b1000 #
b00000000000000000000000011110000 &
b00000000 '
b00000000 (
1*
b1000 +
b0000000000000000 ,
b11111111 -
#121000
b11011111 "
b0101 #
b00000000000000000000000011110010 &
b11111110 '
b11111110 (
b0101 +
b1111111111111110 ,
b00011111 -
#122000
b00001011 "
b0001 #
1$
b00000000000000000000000011110100 &
b00010110 '
b00010110 (
0*
b0001 +
b0000000000010110 ,
b00000001 -
#123000
b11010010 "
b0000 #
0$
b00000000000000000000000011110110 &
b11010010 '
b11010010 (
b0000 +
b1111111111010010 ,
b00000000 -
#124000
b10100110 "
b1110 #
1$
b00000000000000000000000011111000 &
b00000000 '
b10000000 (
1)
b1000 +
b1010011000000000 ,
b11111111 -
#125000
b10101101 "
b00000000000000000000000011111010 &
b1010110100000000 ,
#126000
b00001000 "
b1101 #
b00000000000000000000000011111100 &
b01111111 (
b0000100000000000 ,
#127000
b01101001 "
b0100 #
b00000000000000000000000011111110 &
b10010000 '
b0100 +
b0000011010010000 ,
b00001111 -
#128000
b10110111 "
b1100 #
b00000000000000000000000100000000 &
b00000000 '
b10000000 (
b1000 +
b1011011100000000 ,
b11111111 -
#129000
b00111000 "
b0000 #
b00000000000000000000000100000010 &
b00111000 '
b00111000 (
0)
b0000 +
b0000000000111000 ,
b00000000 -
#130000
b01100001 "
b1001 #
b00000000000000000000000100000100 &
b00000000 '
b01111111 (
1)
b1000 +
b0110000100000000 ,
b11111111 -
#131000
b00101111 "
b1010 #
0$
b00000000000000000000000100000110 &
b00000000 (
0)
1*
b0000000000000000 ,
#132000
b00101011 "
b1011 #
1$
b00000000000000000000000100001000 &
b01111111 (
1)
0*
b0010101100000000 ,
#133000
b00111000 "
b0111 #
0$
b00000000000000000000000100001010 &
b00000000 (
0)
1*
b0111 +
b0000000000000000 ,
b01111111 -
