rtl/math/fixed_point/acc/rtl/agr_fxp_accumulator.sv
`timescale 1ns/1ps
// =============================================================================
// AGR-FPGA-IP-Library : agr_fxp_accumulator
// -----------------------------------------------------------------------------
// Project   : AGR-FXP-ACCUMULATOR (stateful fixed-point accumulator)
// Author    : Agrionics Co.
// Standard  : IEEE 1800-2017 SystemVerilog
// -----------------------------------------------------------------------------
// PURPOSE
//   Stateful accumulator: acc[n+1] = acc[n] + in_val (when enabled).
//   This is the registered companion to agr_fxp_mac - the MAC produces
//   acc_next, and this module registers it while adding control signals
//   (clear, load, enable) for real DSP pipeline integration.
//
//   First stateful block in the AGR DSP library. All previous cores
//   (addsub, mult, resize, round, MAC) are purely combinational.
//
// -----------------------------------------------------------------------------
// CONTROL PRIORITY (strict, documented)
// -----------------------------------------------------------------------------
//   rst > clear > load > enable > hold
//
//   This ordering is deliberate:
//   - rst:   safety override, returns to known state
//   - clear: software/control-plane zeroing without full reset
//   - load:  preload a seed value (e.g. bias term, initial condition)
//   - enable: normal accumulation step
//   - hold:   pipeline stall / clock-gating emulation
//
// -----------------------------------------------------------------------------
// NUMERICAL BEHAVIOR
// -----------------------------------------------------------------------------
//   Addition is performed at ACC_W+1 bits internally (sign-extended
//   operands). Overflow is detected on the exact extended sum BEFORE
//   truncation. This is the same "carry full precision, check once"
//   strategy used in agr_fxp_mac.
//
//   When USE_SATURATE=1 and overflow occurs:
//     - Positive overflow -> clamp to MAX =  2^(ACC_W-1) - 1
//     - Negative overflow -> clamp to MIN = -2^(ACC_W-1)
//   When USE_SATURATE=0:
//     - Standard two's complement wrap (low ACC_W bits of exact sum)
//
//   The overflow flag is sticky for one cycle only (purely combinational
//   from the current operation). It does NOT latch - the caller is
//   responsible for capturing it if needed.
//
// -----------------------------------------------------------------------------
// INTEGRATION WITH agr_fxp_mac
// -----------------------------------------------------------------------------
//   Typical DSP pipeline:
//     agr_fxp_mac (.a, .b, .acc(accumulator.acc), .acc_next, .overflow)
//     agr_fxp_accumulator (.in_val(mac.acc_next), .acc(accumulator.acc))
//
//   Or with rounding between MAC and accumulator:
//     agr_fxp_mac -> agr_fxp_round -> agr_fxp_accumulator
//
// -----------------------------------------------------------------------------
// PARAMETERS
//   ACC_W        : accumulator width, signed, >= 1
//   USE_SATURATE : 0 = wrap on overflow, 1 = saturate to MIN/MAX
//
// PORTS
//   clk      : system clock
//   rst      : synchronous reset (highest priority)
//   enable   : accumulate enable (acc = acc + in_val)
//   clear    : synchronous clear to zero
//   load     : load external value into accumulator
//   load_val : value to load when load=1
//   in_val   : value to add when enable=1
//   acc      : current accumulator value
//   overflow : overflow flag for the CURRENT operation
// =============================================================================

`default_nettype none

module agr_fxp_accumulator #(
    parameter int ACC_W        = 32,
    parameter bit USE_SATURATE = 1'b0
) (
    input  logic                     clk,
    input  logic                     rst,

    input  logic                     enable,
    input  logic                     clear,
    input  logic                     load,
    input  logic signed [ACC_W-1:0]  load_val,

    input  logic signed [ACC_W-1:0]  in_val,

    output logic signed [ACC_W-1:0]  acc,
    output logic                     overflow
);

    // -------------------------------------------------------------------
    // Parameter validation
    // -------------------------------------------------------------------
    initial begin
        if (ACC_W < 1)
            $fatal(1, "agr_fxp_accumulator: ACC_W must be >= 1 (got %0d)", ACC_W);
    end

    // -------------------------------------------------------------------
    // Saturation constants
    // -------------------------------------------------------------------
    localparam logic signed [ACC_W-1:0] ACC_MAX = {1'b0, {(ACC_W-1){1'b1}}};
    localparam logic signed [ACC_W-1:0] ACC_MIN = {1'b1, {(ACC_W-1){1'b0}}};
    localparam logic signed [ACC_W:0]   ACC_MAX_EXT = {ACC_MAX[ACC_W-1], ACC_MAX};
    localparam logic signed [ACC_W:0]   ACC_MIN_EXT = {ACC_MIN[ACC_W-1], ACC_MIN};

    // -------------------------------------------------------------------
    // Internal registers
    // -------------------------------------------------------------------
    logic signed [ACC_W-1:0] acc_reg;

    // -------------------------------------------------------------------
    // Next-state computation (combinational)
    // -------------------------------------------------------------------
    // Extended-width addition for exact overflow detection
    logic signed [ACC_W:0] acc_ext;
    logic signed [ACC_W:0] in_ext;
    logic signed [ACC_W:0] sum_ext;

    assign acc_ext = {acc_reg[ACC_W-1], acc_reg};
    assign in_ext  = {in_val[ACC_W-1], in_val};
    assign sum_ext = acc_ext + in_ext;

    // Overflow: sum exceeds ACC_W-bit signed range
    logic acc_overflow;
    assign acc_overflow = (sum_ext > ACC_MAX_EXT) || (sum_ext < ACC_MIN_EXT);

    // Next value based on control priority
    logic signed [ACC_W-1:0] next_acc;
    logic                    next_overflow;

    always_comb begin
        // Default: hold
        next_acc     = acc_reg;
        next_overflow = 1'b0;

        // Priority: rst > clear > load > enable > hold
        if (rst) begin
            next_acc     = '0;
            next_overflow = 1'b0;
        end else if (clear) begin
            next_acc     = '0;
            next_overflow = 1'b0;
        end else if (load) begin
            next_acc     = load_val;
            next_overflow = 1'b0;
        end else if (enable) begin
            if (USE_SATURATE && acc_overflow) begin
                next_acc = sum_ext[ACC_W] ? ACC_MIN : ACC_MAX;
            end else begin
                next_acc = sum_ext[ACC_W-1:0];
            end
            next_overflow = acc_overflow;
        end
        // else: hold (default)
    end

    // -------------------------------------------------------------------
    // Registered state
    // -------------------------------------------------------------------
    always_ff @(posedge clk) begin
        acc_reg  <= next_acc;
        overflow <= next_overflow;
    end

    // -------------------------------------------------------------------
    // Output
    // -------------------------------------------------------------------
    assign acc = acc_reg;

endmodule : agr_fxp_accumulator

`default_nettype wire

rtl/math/fixed_point/acc/tb/tb_agr_fxp_accumulator.sv
`default_nettype none
`timescale 1ns/1ps

module tb_agr_fxp_accumulator;

    localparam int ACC_W = 8;

    logic clk, rst, enable, clear, load;
    logic signed [ACC_W-1:0] load_val, in_val;
    logic signed [ACC_W-1:0] acc;
    logic overflow;

    int errors = 0;
    int checks = 0;

    // Reference model
    logic signed [ACC_W-1:0] ref_acc;
    bit ref_overflow;

    agr_fxp_accumulator #(.ACC_W(ACC_W), .USE_SATURATE(0))
        dut_wrap (.clk, .rst, .enable, .clear, .load, .load_val, .in_val, .acc(acc), .overflow);

    // Saturating instance
    logic signed [ACC_W-1:0] acc_sat;
    logic overflow_sat;
    logic signed [ACC_W-1:0] ref_acc_sat;

    agr_fxp_accumulator #(.ACC_W(ACC_W), .USE_SATURATE(1))
        dut_sat (.clk, .rst, .enable, .clear, .load, .load_val, .in_val, .acc(acc_sat), .overflow(overflow_sat));

    // Clock
    initial clk = 0;
    always #5 clk = ~clk;

    // -------------------------------------------------------------------
    // Helper tasks
    // -------------------------------------------------------------------
    task automatic tick();
        @(negedge clk);
    endtask

    task automatic reset_all();
        rst = 1; enable = 0; clear = 0; load = 0; in_val = 0; load_val = 0;
        tick();
        rst = 0;
        ref_acc = 0; ref_overflow = 0;
        ref_acc_sat = 0;
        tick();
    endtask

    task automatic do_clear();
        clear = 1; enable = 0; load = 0;
        tick();
        clear = 0;
        ref_acc = 0; ref_overflow = 0;
        ref_acc_sat = 0;
    endtask

    task automatic do_load(input logic signed [ACC_W-1:0] val);
        load = 1; load_val = val; enable = 0; clear = 0;
        tick();
        load = 0;
        ref_acc = val; ref_overflow = 0;
        ref_acc_sat = val;
    endtask

    task automatic do_accumulate(input logic signed [ACC_W-1:0] val);
        longint sum, sum_sat;
        enable = 1; in_val = val; clear = 0; load = 0;
        tick();
        enable = 0;

        // Wrap reference
        sum = longint'(ref_acc) + longint'(val);
        if (sum > 127)       begin ref_acc = sum - 256; ref_overflow = 1; end
        else if (sum < -128) begin ref_acc = sum + 256; ref_overflow = 1; end
        else                 begin ref_acc = sum[ACC_W-1:0]; ref_overflow = 0; end

        // Saturate reference
        sum_sat = longint'(ref_acc_sat) + longint'(val);
        if (sum_sat > 127)       ref_acc_sat = 127;
        else if (sum_sat < -128) ref_acc_sat = -128;
        else                     ref_acc_sat = sum_sat[ACC_W-1:0];
    endtask

    task automatic do_hold();
        enable = 0; clear = 0; load = 0;
        tick();
        ref_overflow = 0;
    endtask

    // -------------------------------------------------------------------
    // Check tasks
    // -------------------------------------------------------------------
    task automatic check_acc(string label);
        checks = checks + 1;
        if (acc !== ref_acc) begin
            errors = errors + 1;
            $error("[%s] wrap acc mismatch: exp=%0d got=%0d", label, ref_acc, acc);
        end
    endtask

    task automatic check_acc_sat(string label);
        checks = checks + 1;
        if (acc_sat !== ref_acc_sat) begin
            errors = errors + 1;
            $error("[%s] sat acc mismatch: exp=%0d got=%0d", label, ref_acc_sat, acc_sat);
        end
    endtask

    task automatic check_overflow(string label);
        checks = checks + 1;
        if (overflow !== ref_overflow) begin
            errors = errors + 1;
            $error("[%s] wrap overflow mismatch: exp=%0b got=%0b", label, ref_overflow, overflow);
        end
    endtask

    task automatic check_both(string label);
        check_acc(label);
        check_acc_sat(label);
        check_overflow(label);
    endtask

    // ===================================================================
    // TEST 1: Reset behavior
    // ===================================================================
    task automatic test_reset_behavior();
        $display("--- Test 1: Reset behavior ---");
        // Reset clears state
        do_accumulate(50);
        do_accumulate(30);
        check_both("after accumulate before reset");
        reset_all();
        check_both("after reset - should be 0");
        // Reset during accumulation
        do_accumulate(10);
        rst = 1; enable = 1; in_val = 99;
        tick();
        rst = 0; enable = 0;
        ref_acc = 0; ref_acc_sat = 0; ref_overflow = 0;
        check_both("reset beats enable");
        $display("  done (%0d checks)", checks);
    endtask

    // ===================================================================
    // TEST 2: Clear behavior
    // ===================================================================
    task automatic test_clear_behavior();
        $display("--- Test 2: Clear behavior ---");
        do_accumulate(50);
        do_clear();
        check_both("after clear - should be 0");
        // Clear from negative
        do_accumulate(-100);
        do_clear();
        check_both("clear from negative");
        // Clear beats enable
        do_accumulate(10);
        clear = 1; enable = 1; in_val = 50;
        tick();
        clear = 0; enable = 0;
        ref_acc = 0; ref_acc_sat = 0; ref_overflow = 0;
        check_both("clear beats enable");
        $display("  done (%0d checks)", checks);
    endtask

    // ===================================================================
    // TEST 3: Load behavior
    // ===================================================================
    task automatic test_load_behavior();
        $display("--- Test 3: Load behavior ---");
        do_load(42);
        check_both("load positive");
        do_load(-100);
        check_both("load negative");
        do_load(0);
        check_both("load zero");
        do_load(127);
        check_both("load MAX");
        do_load(-128);
        check_both("load MIN");
        // Load beats enable
        do_accumulate(10);
        load = 1; load_val = 77; enable = 1; in_val = 99;
        tick();
        load = 0; enable = 0;
        ref_acc = 77; ref_acc_sat = 77; ref_overflow = 0;
        check_both("load beats enable");
        $display("  done (%0d checks)", checks);
    endtask

    // ===================================================================
    // TEST 4: Hold behavior
    // ===================================================================
    task automatic test_hold_behavior();
        $display("--- Test 4: Hold behavior ---");
        do_load(55);
        do_hold();
        check_both("hold after load");
        do_hold();
        check_both("hold twice");
        do_accumulate(10);
        do_hold();
        check_both("hold after accumulate");
        do_hold();
        check_both("hold twice more");
        $display("  done (%0d checks)", checks);
    endtask

    // ===================================================================
    // TEST 5: Control priority (exhaustive pairs)
    // ===================================================================
    task automatic test_priority_exhaustive();
        $display("--- Test 5: Priority exhaustive ---");
        // reset > clear
        rst=1; clear=1; tick(); rst=0; clear=0;
        ref_acc=0; ref_acc_sat=0; ref_overflow=0;
        check_both("reset > clear");
        // reset > load
        rst=1; load=1; load_val=55; tick(); rst=0; load=0;
        check_both("reset > load");
        // reset > enable
        rst=1; enable=1; in_val=99; tick(); rst=0; enable=0;
        check_both("reset > enable");
        // clear > load
        do_accumulate(30);
        clear=1; load=1; load_val=88; tick(); clear=0; load=0;
        ref_acc=0; ref_acc_sat=0; ref_overflow=0;
        check_both("clear > load");
        // clear > enable
        clear=1; enable=1; in_val=77; tick(); clear=0; enable=0;
        check_both("clear > enable");
        // load > enable
        load=1; load_val=33; enable=1; in_val=99; tick(); load=0; enable=0;
        ref_acc=33; ref_acc_sat=33; ref_overflow=0;
        check_both("load > enable");
        // enable > hold (implicit - tested in hold test)
        // Simultaneous all except reset
        clear=1; load=1; load_val=11; enable=1; in_val=22;
        tick(); clear=0; load=0; enable=0;
        ref_acc=0; ref_acc_sat=0; ref_overflow=0;
        check_both("clear beats load+enable");
        $display("  done (%0d checks)", checks);
    endtask

    // ===================================================================
    // TEST 6: Transition cases
    // ===================================================================
    task automatic test_transitions();
        $display("--- Test 6: Transition cases ---");
        // accumulate -> clear -> accumulate
        do_accumulate(40); do_clear(); do_accumulate(15);
        check_both("acc->clear->acc");
        // load -> accumulate -> load -> accumulate
        do_load(10); do_accumulate(5); do_load(-30); do_accumulate(7);
        check_both("load->acc->load->acc");
        // accumulate -> overflow -> clear -> accumulate
        do_accumulate(100); do_accumulate(50);
        check_overflow("overflow detected");
        do_clear(); do_accumulate(20);
        check_both("after overflow+clear");
        // rapid mode switching
        for (int i = 0; i < 20; i++) begin
            tick();
            if (i % 4 == 0)      do_accumulate(1);
            else if (i % 4 == 1) do_hold();
            else if (i % 4 == 2) do_clear();
            else                 do_load(i);
        end
        check_both("rapid switching");
        $display("  done (%0d checks)", checks);
    endtask

    // ===================================================================
    // TEST 7: Overflow wrap mode (exhaustive boundaries)
    // ===================================================================
    task automatic test_overflow_wrap();
        longint sum;
        $display("--- Test 7: Overflow wrap mode ---");
        reset_all();
        // Just below positive overflow: 126+1=127 (no overflow)
        do_load(126); do_accumulate(1);
        sum = 127;
        ref_acc = sum[ACC_W-1:0]; ref_overflow = 0; ref_acc_sat = 127;
        check_both("126+1=127 no overflow");
        // At positive overflow: 127+1=128 -> -128 (overflow)
        do_accumulate(1);
        sum = 128;
        ref_acc = -128; ref_overflow = 1; ref_acc_sat = 127;
        check_both("127+1=128 overflow->-128 wrap, 127 sat");
        // Far positive overflow: 127+100=227 -> -29
        do_load(127); do_accumulate(100);
        sum = 227;
        ref_acc = sum - 256; ref_overflow = 1; ref_acc_sat = 127;
        check_both("127+100 overflow");
        // Just above negative overflow: -128+1=-127 (no overflow)
        do_load(-128); do_accumulate(1);
        sum = -127;
        ref_acc = -127; ref_overflow = 0; ref_acc_sat = -127;
        check_both("-128+1=-127 no overflow");
        // At negative overflow: -128-1=-129 -> 127 (overflow)
        do_load(-128); do_accumulate(-1);
        sum = -129;
        ref_acc = 127; ref_overflow = 1; ref_acc_sat = -128;
        check_both("-128-1=-129 overflow->127 wrap, -128 sat");
        // Far negative overflow: -128-100=-228 -> 28
        do_load(-128); do_accumulate(-100);
        sum = -228;
        ref_acc = sum + 256; ref_overflow = 1; ref_acc_sat = -128;
        check_both("-128-100 overflow");
        // Min+Max: -128+127=-1 (no overflow)
        do_load(-128); do_accumulate(127);
        sum = -1;
        ref_acc = -1; ref_overflow = 0; ref_acc_sat = -1;
        check_both("-128+127=-1 no overflow");
        // Max+Min: 127-128=-1 (no overflow)
        do_load(127); do_accumulate(-128);
        sum = -1;
        ref_acc = -1; ref_overflow = 0; ref_acc_sat = -1;
        check_both("127-128=-1 no overflow");
        $display("  done (%0d checks)", checks);
    endtask

    // ===================================================================
    // TEST 8: Long sequences (FIR-like)
    // ===================================================================
    task automatic test_long_sequences();
        $display("--- Test 8: Long sequences ---");
        reset_all();
        // Sequence of 100 small positive adds
        for (int i = 0; i < 100; i++) do_accumulate(1);
        check_both("100x1=100");
        // Sequence of 100 small negative adds
        for (int i = 0; i < 200; i++) do_accumulate(-1);
        check_both("100-200=-100");
        // Alternating signs (sawtooth)
        for (int i = 0; i < 50; i++) begin
            do_accumulate(10);
            do_accumulate(-7);
        end;
        check_both("50x(10-7)=150");
        // Sweep from MIN to MAX
        do_load(-128);
        for (int i = 0; i < 256; i++) do_accumulate(1);
        check_both("-128+256=128 wraps to -128? No: -128+256=128 overflow->-128 wrap");
        $display("  done (%0d checks)", checks);
    endtask

    // ===================================================================
    // TEST 9: Overflow flag timing
    // ===================================================================
    task automatic test_overflow_flag();
        integer i;
        $display("--- Test 9: Overflow flag timing ---");
        reset_all();
        do_load(127);
        do_accumulate(1);
        check_overflow("127+1 overflow");
        do_accumulate(1);
        check_overflow("-128+1=-127 no overflow");
        do_load(100);
        do_accumulate(50);
        check_overflow("100+50=150 overflow");
        do_accumulate(50);
        check_overflow("-106+50=-56 no overflow");
        do_accumulate(50);
        check_overflow("-56+50=-6 no overflow");
        do_accumulate(50);
        check_overflow("-6+50=44 no overflow");
        $display("  done (%0d checks)", checks);
    endtask

    // ===================================================================
    // TEST 10: Dense random
    // ===================================================================
    task automatic test_random();
        int r, val;
        integer i;
        $display("--- Test 10: Dense random (5000 cycles) ---");
        reset_all();
        for (i = 0; i < 5000; i = i + 1) begin
            tick();
            r = ($urandom() & 32'h7FFFFFFF) % 100;
            val = (($urandom() & 32'h7FFFFFFF) % 256) - 128;
            if (r < 2)        reset_all();
            else if (r < 7)   do_clear();
            else if (r < 15)  do_load(val);
            else if (r < 80)  do_accumulate(val);
            else              do_hold();
            if ((i % 250) == 0) check_both($sformatf("random %0d", i));
        end
        check_both("final random check");
        $display("  done (%0d checks)", checks);
    endtask

    // ===================================================================
    // Main
    // ===================================================================
    initial begin
        $display("=== agr_fxp_accumulator comprehensive testbench ===");
        $display("ACC_W=%0d, testing wrap AND saturate instances", ACC_W);
        reset_all();

        test_reset_behavior();
        test_clear_behavior();
        test_load_behavior();
        test_hold_behavior();
        test_priority_exhaustive();
        test_transitions();
        test_overflow_wrap();
        test_long_sequences();
        test_overflow_flag();
        test_random();

        $display("");
        $display("=== %0d checks run, %0d errors ===", checks, errors);
        if (errors == 0) begin
            $display("*** ALL TESTS PASSED ***");
            $finish;
        end else begin
            $display("*** TEST FAILED: %0d errors ***", errors);
            $stop;
        end
    end

endmodule
`default_nettype wire

rtl/math/fixed_point/acc/sim/wave.vcd
$version Generated by VerilatedVcd $end
$timescale 1ps $end
 $scope module TOP $end
  $scope module tb_agr_fxp_accumulator $end
   $var wire 32 = ACC_W [31:0] $end
   $var wire 1 9 clk $end
   $var wire 1 " rst $end
   $var wire 1 # enable $end
   $var wire 1 $ clear $end
   $var wire 1 % load $end
   $var wire 8 & load_val [7:0] $end
   $var wire 8 ' in_val [7:0] $end
   $var wire 8 3 acc [7:0] $end
   $var wire 1 4 overflow $end
   $var wire 32 : errors [31:0] $end
   $var wire 32 ; checks [31:0] $end
   $var wire 8 ( ref_acc [7:0] $end
   $var wire 1 ) ref_overflow $end
   $var wire 8 5 acc_sat [7:0] $end
   $var wire 1 6 overflow_sat $end
   $var wire 8 * ref_acc_sat [7:0] $end
   $scope module dut_sat $end
    $var wire 32 = ACC_W [31:0] $end
    $var wire 1 > USE_SATURATE $end
    $var wire 1 9 clk $end
    $var wire 1 " rst $end
    $var wire 1 # enable $end
    $var wire 1 $ clear $end
    $var wire 1 % load $end
    $var wire 8 & load_val [7:0] $end
    $var wire 8 ' in_val [7:0] $end
    $var wire 8 5 acc [7:0] $end
    $var wire 1 6 overflow $end
    $var wire 8 ? ACC_MAX [7:0] $end
    $var wire 8 @ ACC_MIN [7:0] $end
    $var wire 9 A ACC_MAX_EXT [8:0] $end
    $var wire 9 B ACC_MIN_EXT [8:0] $end
    $var wire 8 5 acc_reg [7:0] $end
    $var wire 9 7 acc_ext [8:0] $end
    $var wire 9 < in_ext [8:0] $end
    $var wire 9 + sum_ext [8:0] $end
    $var wire 1 , acc_overflow $end
    $var wire 8 - next_acc [7:0] $end
    $var wire 1 . next_overflow $end
   $upscope $end
   $scope module dut_wrap $end
    $var wire 32 = ACC_W [31:0] $end
    $var wire 1 C USE_SATURATE $end
    $var wire 1 9 clk $end
    $var wire 1 " rst $end
    $var wire 1 # enable $end
    $var wire 1 $ clear $end
    $var wire 1 % load $end
    $var wire 8 & load_val [7:0] $end
    $var wire 8 ' in_val [7:0] $end
    $var wire 8 3 acc [7:0] $end
    $var wire 1 4 overflow $end
    $var wire 8 ? ACC_MAX [7:0] $end
    $var wire 8 @ ACC_MIN [7:0] $end
    $var wire 9 A ACC_MAX_EXT [8:0] $end
    $var wire 9 B ACC_MIN_EXT [8:0] $end
    $var wire 8 3 acc_reg [7:0] $end
    $var wire 9 8 acc_ext [8:0] $end
    $var wire 9 < in_ext [8:0] $end
    $var wire 9 / sum_ext [8:0] $end
    $var wire 1 0 acc_overflow $end
    $var wire 8 1 next_acc [7:0] $end
    $var wire 1 2 next_overflow $end
   $upscope $end
  $upscope $end
 $upscope $end
$enddefinitions $end


#0
1"
0#
0$
0%
b00000000 &
b00000000 '
b00000000 (
0)
b00000000 *
b000000000 +
0,
b00000000 -
0.
b000000000 /
00
b00000000 1
02
b00000000 3
04
b00000000 5
06
b000000000 7
b000000000 8
09
b00000000000000000000000000000000 :
b00000000000000000000000000000000 ;
b000000000 <
b00000000000000000000000000001000 =
1>
b01111111 ?
b10000000 @
b001111111 A
b110000000 B
0C
#5000
19
#10000
0"
09
#15000
19
#20000
1#
b00110010 '
b000110010 +
b00110010 -
b000110010 /
b00110010 1
09
b000110010 <
#25000
b001100100 +
b01100100 -
b001100100 /
b01100100 1
b00110010 3
b00110010 5
b000110010 7
b000110010 8
19
#30000
b00011110 '
b00110010 (
b00110010 *
b001010000 +
b01010000 -
b001010000 /
b01010000 1
09
b000011110 <
#35000
b001101110 +
b01101110 -
b001101110 /
b01101110 1
b01010000 3
b01010000 5
b001010000 7
b001010000 8
19
#40000
1"
0#
b00000000 '
b01010000 (
b01010000 *
b001010000 +
b00000000 -
b001010000 /
b00000000 1
09
b00000000000000000000000000000011 ;
b000000000 <
#45000
b000000000 +
b000000000 /
b00000000 3
b00000000 5
b000000000 7
b000000000 8
19
#50000
0"
b00000000 (
b00000000 *
09
#55000
19
#60000
1#
b00001010 '
b000001010 +
b00001010 -
b000001010 /
b00001010 1
09
b00000000000000000000000000000110 ;
b000001010 <
#65000
b000010100 +
b00010100 -
b000010100 /
b00010100 1
b00001010 3
b00001010 5
b000001010 7
b000001010 8
19
#70000
1"
b01100011 '
b00001010 (
b00001010 *
b001101101 +
b00000000 -
b001101101 /
b00000000 1
09
b001100011 <
#75000
b001100011 +
b001100011 /
b00000000 3
b00000000 5
b000000000 7
b000000000 8
19
#80000
0"
b00110010 '
b00000000 (
b00000000 *
b000110010 +
b00110010 -
b000110010 /
b00110010 1
09
b00000000000000000000000000001001 ;
b000110010 <
#85000
b001100100 +
b01100100 -
b001100100 /
b01100100 1
b00110010 3
b00110010 5
b000110010 7
b000110010 8
19
#90000
0#
1$
b00110010 (
b00110010 *
b00000000 -
b00000000 1
09
#95000
b000110010 +
b000110010 /
b00000000 3
b00000000 5
b000000000 7
b000000000 8
19
#100000
1#
0$
b10011100 '
b00000000 (
b00000000 *
b110011100 +
b10011100 -
b110011100 /
b10011100 1
09
b00000000000000000000000000001100 ;
b110011100 <
#105000
b100111000 +
1,
b10000000 -
1.
b100111000 /
10
b00111000 1
12
b10011100 3
b10011100 5
b110011100 7
b110011100 8
19
#110000
0#
1$
b10011100 (
b10011100 *
b00000000 -
0.
b00000000 1
02
09
#115000
b110011100 +
0,
b110011100 /
00
b00000000 3
b00000000 5
b000000000 7
b000000000 8
19
#120000
1#
0$
b00001010 '
b00000000 (
b00000000 *
b000001010 +
b00001010 -
b000001010 /
b00001010 1
09
b00000000000000000000000000001111 ;
b000001010 <
#125000
b000010100 +
b00010100 -
b000010100 /
b00010100 1
b00001010 3
b00001010 5
b000001010 7
b000001010 8
19
#130000
1$
b00110010 '
b00001010 (
b00001010 *
b000111100 +
b00000000 -
b000111100 /
b00000000 1
09
b000110010 <
#135000
b000110010 +
b000110010 /
b00000000 3
b00000000 5
b000000000 7
b000000000 8
19
#140000
0#
0$
1%
b00101010 &
b00000000 (
b00000000 *
b00101010 -
b00101010 1
09
b00000000000000000000000000010010 ;
#145000
b001011100 +
b001011100 /
b00101010 3
b00101010 5
b000101010 7
b000101010 8
19
#150000
b10011100 &
b00101010 (
b00101010 *
b10011100 -
b10011100 1
09
b00000000000000000000000000010101 ;
#155000
b111001110 +
b111001110 /
b10011100 3
b10011100 5
b110011100 7
b110011100 8
19
#160000
b00000000 &
b10011100 (
b10011100 *
b00000000 -
b00000000 1
09
b00000000000000000000000000011000 ;
#165000
b000110010 +
b000110010 /
b00000000 3
b00000000 5
b000000000 7
b000000000 8
19
#170000
b01111111 &
b00000000 (
b00000000 *
b01111111 -
b01111111 1
09
b00000000000000000000000000011011 ;
#175000
b010110001 +
1,
b010110001 /
10
b01111111 3
b01111111 5
b001111111 7
b001111111 8
19
#180000
b10000000 &
b01111111 (
b01111111 *
b10000000 -
b10000000 1
09
b00000000000000000000000000011110 ;
#185000
b110110010 +
0,
b110110010 /
00
b10000000 3
b10000000 5
b110000000 7
b110000000 8
19
#190000
1#
0%
b00001010 '
b10000000 (
b10000000 *
b110001010 +
b10001010 -
b110001010 /
b10001010 1
09
b00000000000000000000000000100001 ;
b000001010 <
#195000
b110010100 +
b10010100 -
b110010100 /
b10010100 1
b10001010 3
b10001010 5
b110001010 7
b110001010 8
19
#200000
1%
b01001101 &
b01100011 '
b10001010 (
b10001010 *
b111101101 +
b01001101 -
b111101101 /
b01001101 1
09
b001100011 <
#205000
b010110000 +
1,
b010110000 /
10
b01001101 3
b01001101 5
b001001101 7
b001001101 8
19
#210000
0#
b00110111 &
b01001101 (
b01001101 *
b00110111 -
b00110111 1
09
b00000000000000000000000000100100 ;
#215000
b010011010 +
b010011010 /
b00110111 3
b00110111 5
b000110111 7
b000110111 8
19
#220000
0%
b00110111 (
b00110111 *
09
#225000
19
#230000
09
b00000000000000000000000000100111 ;
#235000
19
#240000
1#
b00001010 '
b001000001 +
0,
b01000001 -
b001000001 /
00
b01000001 1
09
b00000000000000000000000000101010 ;
b000001010 <
#245000
b001001011 +
b01001011 -
b001001011 /
b01001011 1
b01000001 3
b01000001 5
b001000001 7
b001000001 8
19
#250000
0#
b01000001 (
b01000001 *
b01000001 -
b01000001 1
09
#255000
19
#260000
09
b00000000000000000000000000101101 ;
#265000
19
#270000
1"
1$
b00000000 -
b00000000 1
09
b00000000000000000000000000110000 ;
#275000
b000001010 +
b000001010 /
b00000000 3
b00000000 5
b000000000 7
b000000000 8
19
#280000
0$
1%
b00000000 (
b00000000 *
09
b00000000000000000000000000110011 ;
#285000
19
#290000
1#
0%
b01100011 '
b001100011 +
b001100011 /
09
b00000000000000000000000000110110 ;
b001100011 <
#295000
19
#300000
0"
b00011110 '
b000011110 +
b00011110 -
b000011110 /
b00011110 1
09
b00000000000000000000000000111001 ;
b000011110 <
#305000
b000111100 +
b00111100 -
b000111100 /
b00111100 1
b00011110 3
b00011110 5
b000011110 7
b000011110 8
19
#310000
0#
1$
1%
b01011000 &
b00011110 (
b00011110 *
b00000000 -
b00000000 1
09
#315000
b000011110 +
b000011110 /
b00000000 3
b00000000 5
b000000000 7
b000000000 8
19
#320000
1#
0%
b01001101 '
b00000000 (
b00000000 *
b001001101 +
b001001101 /
09
b00000000000000000000000000111100 ;
b001001101 <
#325000
19
#330000
0$
1%
b00100001 &
b01100011 '
b001100011 +
b00100001 -
b001100011 /
b00100001 1
09
b00000000000000000000000000111111 ;
b001100011 <
#335000
b010000100 +
1,
b010000100 /
10
b00100001 3
b00100001 5
b000100001 7
b000100001 8
19
#340000
1$
b00001011 &
b00010110 '
b00100001 (
b00100001 *
b000110111 +
0,
b00000000 -
b000110111 /
00
b00000000 1
09
b00000000000000000000000001000010 ;
b000010110 <
#345000
b000010110 +
b000010110 /
b00000000 3
b00000000 5
b000000000 7
b000000000 8
19
#350000
0$
0%
b00101000 '
b00000000 (
b00000000 *
b000101000 +
b00101000 -
b000101000 /
b00101000 1
09
b00000000000000000000000001000101 ;
b000101000 <
#355000
b001010000 +
b01010000 -
b001010000 /
b01010000 1
b00101000 3
b00101000 5
b000101000 7
b000101000 8
19
#360000
0#
1$
b00101000 (
b00101000 *
b00000000 -
b00000000 1
09
#365000
b000101000 +
b000101000 /
b00000000 3
b00000000 5
b000000000 7
b000000000 8
19
#370000
1#
0$
b00001111 '
b00000000 (
b00000000 *
b000001111 +
b00001111 -
b000001111 /
b00001111 1
09
b000001111 <
#375000
b000011110 +
b00011110 -
b000011110 /
b00011110 1
b00001111 3
b00001111 5
b000001111 7
b000001111 8
19
#380000
0#
1%
b00001010 &
b00001111 (
b00001111 *
b00001010 -
b00001010 1
09
b00000000000000000000000001001000 ;
#385000
b000011001 +
b000011001 /
b00001010 3
b00001010 5
b000001010 7
b000001010 8
19
#390000
1#
0%
b00000101 '
b00001010 (
b00001010 *
b000001111 +
b00001111 -
b000001111 /
b00001111 1
09
b000000101 <
#395000
b000010100 +
b00010100 -
b000010100 /
b00010100 1
b00001111 3
b00001111 5
b000001111 7
b000001111 8
19
#400000
0#
1%
b11100010 &
b00001111 (
b00001111 *
b11100010 -
b11100010 1
09
#405000
b111100111 +
b111100111 /
b11100010 3
b11100010 5
b111100010 7
b111100010 8
19
#410000
1#
0%
b00000111 '
b11100010 (
b11100010 *
b111101001 +
b11101001 -
b111101001 /
b11101001 1
09
b000000111 <
#415000
b111110000 +
b11110000 -
b111110000 /
b11110000 1
b11101001 3
b11101001 5
b111101001 7
b111101001 8
19
#420000
b01100100 '
b11101001 (
b11101001 *
b001001101 +
b01001101 -
b001001101 /
b01001101 1
09
b00000000000000000000000001001011 ;
b001100100 <
#425000
b010110001 +
1,
b01111111 -
1.
b010110001 /
10
b10110001 1
12
b01001101 3
b01001101 5
b001001101 7
b001001101 8
19
#430000
b00110010 '
b01001101 (
b01001101 *
b001111111 +
0,
0.
b001111111 /
00
b01111111 1
02
09
b000110010 <
#435000
b010110001 +
1,
1.
b010110001 /
10
b10110001 1
12
b01111111 3
b01111111 5
b001111111 7
b001111111 8
19
#440000
0#
1$
b01111111 (
b01111111 *
b00000000 -
0.
b00000000 1
02
09
b00000000000000000000000001001100 ;
#445000
b000110010 +
0,
b000110010 /
00
b00000000 3
b00000000 5
b000000000 7
b000000000 8
19
