rtl/math/complex/complex_addsub/rtl/agr_complex_addsub.sv
// =============================================================================
// AGR-FPGA-IP-Library : agr_complex_addsub
// -----------------------------------------------------------------------------
// Project   : AGR-COMPLEX-ADDSUB (fixed-point complex adder/subtractor)
// Author    : Agrionics Co.
// Standard  : IEEE 1800-2017 SystemVerilog
// -----------------------------------------------------------------------------
// PURPOSE
//   Complex addition and subtraction:
//     ADD (sub=0): out = A + B
//     SUB (sub=1): out = A - B
//
//   Core building block for FFT butterfly stages (radix-2 sum/difference)
//   and complex DSP pipelines. Pairs with agr_complex_mult for complete
//   FFT butterfly: multiply twiddle factors (agr_complex_mult), then
//   add/sub with this module.
//
//   Pure combinational in v1: no clock, no reset, no state.
//
// -----------------------------------------------------------------------------
// ARCHITECTURE (4 explicit stages)
// -----------------------------------------------------------------------------
//   Stage 0: SIGN-EXTEND
//     Each input is sign-extended from IN_W to IN_W+1 bits. The extra
//     guard bit absorbs the worst-case carry from addition or borrow
//     from subtraction. No internal overflow is possible at Stage 1
//     by construction -- two IN_W-bit signed values can never produce
//     a sum/difference requiring more than IN_W+1 bits.
//
//   Stage 1: ADD/SUB (full precision)
//     real_full = sub ? (ar_ext - br_ext) : (ar_ext + br_ext)
//     imag_full = sub ? (ai_ext - bi_ext) : (ai_ext + bi_ext)
//     Computed at IN_W+1 bits. Exact, never wraps internally.
//
//   Stage 2: RESIZE (MSB-aligned toward OUT_W)
//     If OUT_W >= IN_W+1: sign-extend to fill the wider output.
//     If OUT_W <  IN_W+1: keep top OUT_W bits (sign + high-order
//       magnitude), drop the bottom DROP_W bits. This is MSB-aligned
//       truncation -- the sign and relative magnitude are always
//       preserved; only fine resolution is lost.
//
//   Stage 3: OVERFLOW + SATURATION (per-component)
//     Each component independently checked against OUT_W-bit range.
//     overflow = overflow_real OR overflow_imag.
//     Saturation clamps each component to its own MIN/MAX, never
//     cross-contaminating (real overflow does NOT clamp imag).
//
// -----------------------------------------------------------------------------
// BIT GROWTH PROOF
// -----------------------------------------------------------------------------
//   Two IN_W-bit signed values: range [-2^(IN_W-1), 2^(IN_W-1)-1]
//   Sum range: [-2^IN_W, 2^IN_W-2]
//   Difference range: [-2^IN_W+1, 2^IN_W-1]
//   Both fit in IN_W+1 bits (range [-2^IN_W, 2^IN_W-1]).
//   Therefore Stage 1 never wraps internally.
//
// -----------------------------------------------------------------------------
// FFT BUTTERFLY USAGE
// -----------------------------------------------------------------------------
//   Radix-2 DIT butterfly:
//     X = x[0] + x[1]          (use ADD mode)
//     Y = (x[0] - x[1]) * W    (use SUB mode, then agr_complex_mult)
//
//   This module handles the sum/difference portion. Pair with
//   agr_complex_mult for the twiddle-factor multiply.
//
// -----------------------------------------------------------------------------
// PARAMETERS
//   IN_W         : input width, signed, >= 1
//   OUT_W        : output width, signed, >= 1
//   USE_SATURATE : 0 = wrap on overflow, 1 = saturate to MIN/MAX
//
// PORTS
//   a_real, a_imag : first complex operand (IN_W bits)
//   b_real, b_imag : second complex operand (IN_W bits)
//   sub            : 0 = ADD (A+B), 1 = SUB (A-B)
//   out_real       : real component (OUT_W bits)
//   out_imag       : imaginary component (OUT_W bits)
//   overflow       : OR of per-component overflow flags
//
// VERIFICATION
//   Testbench: tb_agr_complex_addsub.sv
//   Checks:   18,069 directed + random (3000 cases × 2 ops × 3 assertions)
//   Status:   ALL PASSING
//   Coverage: simple add/sub, zero, identity (A-A=0), sign combos,
//             MAX/MIN, symmetry (A+B == B+A), 3000 random pairs
//
// DEPENDENCIES
//   None. Standalone module. Pairs with agr_complex_mult for FFT.
// =============================================================================

`default_nettype none
`timescale 1ns/1ps

module agr_complex_addsub #(
    parameter int IN_W         = 16,
    parameter int OUT_W        = 16,
    parameter bit USE_SATURATE = 1'b0
) (
    input  logic signed [IN_W-1:0]  a_real,
    input  logic signed [IN_W-1:0]  a_imag,
    input  logic signed [IN_W-1:0]  b_real,
    input  logic signed [IN_W-1:0]  b_imag,
    input  logic                    sub,

    output logic signed [OUT_W-1:0] out_real,
    output logic signed [OUT_W-1:0] out_imag,
    output logic                    overflow
);

    // -------------------------------------------------------------------
    // Parameter validation (simulation only; ignored by synthesis)
    // -------------------------------------------------------------------
    initial begin
        if (IN_W < 1)
            $fatal(1, "agr_complex_addsub: IN_W must be >= 1 (got %0d)", IN_W);
        if (OUT_W < 1)
            $fatal(1, "agr_complex_addsub: OUT_W must be >= 1 (got %0d)", OUT_W);
    end

    // Derived constants
    localparam int EXT_W       = IN_W + 1;           // Extended width with guard bit
    localparam bit NEEDS_REDUCE = (OUT_W < EXT_W);    // True if we need to drop bits

    // ===================================================================
    // STAGE 0: Sign-extend inputs to EXT_W bits
    //
    // Each IN_W-bit signed input is extended by replicating its sign bit
    // into the new MSB position. This preserves the value while adding
    // one bit of headroom for the subsequent addition/subtraction.
    // ===================================================================
    logic signed [EXT_W-1:0] ar_ext, ai_ext, br_ext, bi_ext;
    assign ar_ext = {a_real[IN_W-1], a_real};
    assign ai_ext = {a_imag[IN_W-1], a_imag};
    assign br_ext = {b_real[IN_W-1], b_real};
    assign bi_ext = {b_imag[IN_W-1], b_imag};

    // ===================================================================
    // STAGE 1: Full-precision add/subtract at EXT_W bits
    //
    // The operation is selected by `sub`:
    //   sub=0: real_full = A + B, imag_full = A + B
    //   sub=1: real_full = A - B, imag_full = A - B
    //
    // Both components use the same `sub` control -- this is a true
    // complex add/sub, not independent per-component control.
    // ===================================================================
    logic signed [EXT_W-1:0] real_full, imag_full;
    assign real_full = sub ? (ar_ext - br_ext) : (ar_ext + br_ext);
    assign imag_full = sub ? (ai_ext - bi_ext) : (ai_ext + bi_ext);

    // ===================================================================
    // STAGE 2: MSB-aligned resize toward OUT_W
    //
    // Two structural cases:
    //   OUT_W >= EXT_W: Output is wider than needed. Sign-extend the
    //     full-precision result into the extra bits (no information lost).
    //   OUT_W <  EXT_W: Output is narrower. Keep the top OUT_W bits
    //     (sign + high-order magnitude), drop the bottom DROP_W bits.
    //     This is MSB-aligned truncation -- the numeric scale is
    //     preserved; only precision is reduced.
    // ===================================================================
    logic signed [OUT_W-1:0] real_resized, imag_resized;

    generate
        if (OUT_W >= EXT_W) begin : gen_expand
            // Pad with sign extension -- no information discarded
            localparam int PAD_W = OUT_W - EXT_W;
            assign real_resized = {{PAD_W{real_full[EXT_W-1]}}, real_full};
            assign imag_resized = {{PAD_W{imag_full[EXT_W-1]}}, imag_full};
        end else begin : gen_reduce
            // MSB-aligned: keep top OUT_W bits of the EXT_W-bit value
            assign real_resized = real_full[EXT_W-1 -: OUT_W];
            assign imag_resized = imag_full[EXT_W-1 -: OUT_W];
        end
    endgenerate

    // ===================================================================
    // STAGE 3: Per-component overflow detection + optional saturation
    //
    // Overflow is checked against the OUT_W-bit signed range using the
    // FULL-precision (EXT_W-bit) values -- never against the already-
    // truncated resized values. This guarantees that overflow reflects
    // the true mathematical result, not a post-truncation artifact.
    //
    // Saturation is gated per-component: out_real only clamps because
    // overflow_real fired, never because overflow_imag did. Each clamp
    // direction (MIN vs MAX) is chosen from that component's own sign.
    // ===================================================================
    localparam logic signed [OUT_W-1:0] OUT_MAX = {1'b0, {(OUT_W-1){1'b1}}};
    localparam logic signed [OUT_W-1:0] OUT_MIN = {1'b1, {(OUT_W-1){1'b0}}};

    logic overflow_real, overflow_imag;
    assign overflow_real = NEEDS_REDUCE ? ((real_full > OUT_MAX) || (real_full < OUT_MIN)) : 1'b0;
    assign overflow_imag = NEEDS_REDUCE ? ((imag_full > OUT_MAX) || (imag_full < OUT_MIN)) : 1'b0;
    assign overflow = overflow_real | overflow_imag;

    // Output: saturate on overflow (per-component), otherwise pass through
    assign out_real = (USE_SATURATE && overflow_real) ? (real_full < 0 ? OUT_MIN : OUT_MAX)
                                                         : real_resized;
    assign out_imag = (USE_SATURATE && overflow_imag) ? (imag_full < 0 ? OUT_MIN : OUT_MAX)
                                                         : imag_resized;

endmodule : agr_complex_addsub

`default_nettype wire

rtl/math/complex/complex_addsub/tb/tb_agr_complex_addsub.sv
`default_nettype none
`timescale 1ns/1ps

module tb_agr_complex_addsub;

    localparam int IN_W = 8;
    localparam int OUT_W = 16;

    logic signed [IN_W-1:0] a_real, a_imag, b_real, b_imag;
    logic sub;
    logic signed [OUT_W-1:0] out_real, out_imag;
    logic overflow;

    int errors = 0;
    int checks = 0;

    agr_complex_addsub #(.IN_W(IN_W), .OUT_W(OUT_W), .USE_SATURATE(0))
        dut (.a_real, .a_imag, .b_real, .b_imag, .sub, .out_real, .out_imag, .overflow);

    task automatic test;
        input longint ar, ai, br, bi;
        input bit op_sub;
        input longint exp_r, exp_i;
        input bit exp_ovf;
        longint full_r, full_i;
        begin
            a_real = ar[IN_W-1:0]; a_imag = ai[IN_W-1:0];
            b_real = br[IN_W-1:0]; b_imag = bi[IN_W-1:0];
            sub = op_sub;
            #1;

            // Golden model: 64-bit math
            if (op_sub) begin
                full_r = ar - br;
                full_i = ai - bi;
            end else begin
                full_r = ar + br;
                full_i = ai + bi;
            end

            checks = checks + 3;
            if (out_real !== full_r || out_imag !== full_i || overflow !== exp_ovf) begin
                errors = errors + 1;
                $display("FAIL: (%0d+j%0d) %s (%0d+j%0d) exp=(%0d+j%0d,ovf=%0b) got=(%0d+j%0d,ovf=%0b)",
                       ar, ai, op_sub ? "-" : "+", br, bi, full_r, full_i, exp_ovf, out_real, out_imag, overflow);
            end
        end
    endtask

    integer i;
    longint ar, ai, br, bi;

    initial begin
        $display("=== agr_complex_addsub testbench ===");
        $display("IN_W=%0d, OUT_W=%0d", IN_W, OUT_W);

        $display("--- Simple ADD ---");
        test(1,0,1,0, 0, 2,0,0);
        test(1,1,1,1, 0, 2,2,0);
        test(5,3,2,7, 0, 7,10,0);

        $display("--- Simple SUB ---");
        test(5,3,2,7, 1, 3,-4,0);
        test(1,1,1,1, 1, 0,0,0);

        $display("--- Zero ---");
        test(0,0,5,5, 0, 5,5,0);
        test(5,5,0,0, 0, 5,5,0);
        test(0,0,0,0, 0, 0,0,0);
        test(0,0,0,0, 1, 0,0,0);

        $display("--- Identity (A-A=0) ---");
        test(5,3,5,3, 1, 0,0,0);
        test(-2,7,-2,7, 1, 0,0,0);

        $display("--- Sign combinations ---");
        test(2,3,4,5, 0, 6,8,0);
        test(-2,3,4,5, 0, 2,8,0);
        test(2,-3,4,5, 0, 6,2,0);
        test(-2,-3,-4,-5, 0, -6,-8,0);
        test(-2,-3,4,5, 1, -6,-8,0);

        $display("--- MAX/MIN ---");
        test(127,0,127,0, 0, 254,0,0);
        test(-128,0,-128,0, 0, -256,0,0);
        test(127,0,-128,0, 1, 255,0,0);
        test(127,127,127,127, 0, 254,254,0);
        test(127,127,-128,-128, 1, 255,255,0);

        $display("--- Symmetry ---");
        test(2,3,4,5, 0, 6,8,0);
        test(4,5,2,3, 0, 6,8,0);

        $display("--- Random (3000 cases) ---");
        for (i = 0; i < 3000; i = i + 1) begin
            ar = (($urandom() & 32'h7FFFFFFF) % 256) - 128;
            ai = (($urandom() & 32'h7FFFFFFF) % 256) - 128;
            br = (($urandom() & 32'h7FFFFFFF) % 256) - 128;
            bi = (($urandom() & 32'h7FFFFFFF) % 256) - 128;
            test(ar, ai, br, bi, 0, ar+br, ai+bi, 0);
            test(ar, ai, br, bi, 1, ar-br, ai-bi, 0);
        end

        $display("");
        $display("=== %0d checks run, %0d errors ===", checks, errors);
        if (errors == 0) $display("*** ALL TESTS PASSED ***");
        else $display("*** TEST FAILED ***");
        $finish;
    end

endmodule
`default_nettype wire

rtl/math/complex/complex_addsub/sim/wave.vcd
$version Generated by VerilatedVcd $end
$timescale 1ps $end
 $scope module TOP $end
  $scope module tb_agr_complex_addsub $end
   $var wire 32 : IN_W [31:0] $end
   $var wire 32 ; OUT_W [31:0] $end
   $var wire 8 " a_real [7:0] $end
   $var wire 8 # a_imag [7:0] $end
   $var wire 8 $ b_real [7:0] $end
   $var wire 8 % b_imag [7:0] $end
   $var wire 1 & sub $end
   $var wire 16 2 out_real [15:0] $end
   $var wire 16 3 out_imag [15:0] $end
   $var wire 1 < overflow $end
   $var wire 32 ' errors [31:0] $end
   $var wire 32 ( checks [31:0] $end
   $var wire 32 ) i [31:0] $end
   $var wire 64 * ar [63:0] $end
   $var wire 64 , ai [63:0] $end
   $var wire 64 . br [63:0] $end
   $var wire 64 0 bi [63:0] $end
   $scope module dut $end
    $var wire 32 : IN_W [31:0] $end
    $var wire 32 ; OUT_W [31:0] $end
    $var wire 1 = USE_SATURATE $end
    $var wire 8 " a_real [7:0] $end
    $var wire 8 # a_imag [7:0] $end
    $var wire 8 $ b_real [7:0] $end
    $var wire 8 % b_imag [7:0] $end
    $var wire 1 & sub $end
    $var wire 16 2 out_real [15:0] $end
    $var wire 16 3 out_imag [15:0] $end
    $var wire 1 < overflow $end
    $var wire 32 > EXT_W [31:0] $end
    $var wire 1 = NEEDS_REDUCE $end
    $var wire 9 4 ar_ext [8:0] $end
    $var wire 9 5 ai_ext [8:0] $end
    $var wire 9 6 br_ext [8:0] $end
    $var wire 9 7 bi_ext [8:0] $end
    $var wire 9 8 real_full [8:0] $end
    $var wire 9 9 imag_full [8:0] $end
    $var wire 16 2 real_resized [15:0] $end
    $var wire 16 3 imag_resized [15:0] $end
    $var wire 16 ? OUT_MAX [15:0] $end
    $var wire 16 @ OUT_MIN [15:0] $end
    $var wire 1 < overflow_real $end
    $var wire 1 < overflow_imag $end
    $scope module gen_expand $end
     $var wire 32 A PAD_W [31:0] $end
    $upscope $end
   $upscope $end
  $upscope $end
 $upscope $end
$enddefinitions $end


#0
b00000001 "
b00000000 #
b00000001 $
b00000000 %
0&
b00000000000000000000000000000000 '
b00000000000000000000000000000000 (
b00000000000000000000000000000000 )
b0000000000000000000000000000000000000000000000000000000000000000 *
b0000000000000000000000000000000000000000000000000000000000000000 ,
b0000000000000000000000000000000000000000000000000000000000000000 .
b0000000000000000000000000000000000000000000000000000000000000000 0
b0000000000000010 2
b0000000000000000 3
b000000001 4
b000000000 5
b000000001 6
b000000000 7
b000000010 8
b000000000 9
b00000000000000000000000000001000 :
b00000000000000000000000000010000 ;
0<
0=
b00000000000000000000000000001001 >
b0111111111111111 ?
b1000000000000000 @
b00000000000000000000000000000111 A
#1000
b00000001 #
b00000001 %
b00000000000000000000000000000011 (
b0000000000000010 3
b000000001 5
b000000001 7
b000000010 9
#2000
b00000101 "
b00000011 #
b00000010 $
b00000111 %
b00000000000000000000000000000110 (
b0000000000000111 2
b0000000000001010 3
b000000101 4
b000000011 5
b000000010 6
b000000111 7
b000000111 8
b000001010 9
#3000
1&
b00000000000000000000000000001001 (
b0000000000000011 2
b1111111111111100 3
b000000011 8
b111111100 9
#4000
b00000001 "
b00000001 #
b00000001 $
b00000001 %
b00000000000000000000000000001100 (
b0000000000000000 2
b0000000000000000 3
b000000001 4
b000000001 5
b000000001 6
b000000001 7
b000000000 8
b000000000 9
#5000
b00000000 "
b00000000 #
b00000101 $
b00000101 %
0&
b00000000000000000000000000001111 (
b0000000000000101 2
b0000000000000101 3
b000000000 4
b000000000 5
b000000101 6
b000000101 7
b000000101 8
b000000101 9
#6000
b00000101 "
b00000101 #
b00000000 $
b00000000 %
b00000000000000000000000000010010 (
b000000101 4
b000000101 5
b000000000 6
b000000000 7
#7000
b00000000 "
b00000000 #
b00000000000000000000000000010101 (
b0000000000000000 2
b0000000000000000 3
b000000000 4
b000000000 5
b000000000 8
b000000000 9
#8000
1&
b00000000000000000000000000011000 (
#9000
b00000101 "
b00000011 #
b00000101 $
b00000011 %
b00000000000000000000000000011011 (
b000000101 4
b000000011 5
b000000101 6
b000000011 7
#10000
b11111110 "
b00000111 #
b11111110 $
b00000111 %
b00000000000000000000000000011110 (
b111111110 4
b000000111 5
b111111110 6
b000000111 7
#11000
b00000010 "
b00000011 #
b00000100 $
b00000101 %
0&
b00000000000000000000000000100001 (
b0000000000000110 2
b0000000000001000 3
b000000010 4
b000000011 5
b000000100 6
b000000101 7
b000000110 8
b000001000 9
#12000
b11111110 "
b00000000000000000000000000100100 (
b0000000000000010 2
b111111110 4
b000000010 8
#13000
b00000010 "
b11111101 #
b00000000000000000000000000100111 (
b0000000000000110 2
b0000000000000010 3
b000000010 4
b111111101 5
b000000110 8
b000000010 9
#14000
b11111110 "
b11111100 $
b11111011 %
b00000000000000000000000000101010 (
b1111111111111010 2
b1111111111111000 3
b111111110 4
b111111100 6
b111111011 7
b111111010 8
b111111000 9
#15000
b00000100 $
b00000101 %
1&
b00000000000000000000000000101101 (
b000000100 6
b000000101 7
#16000
b01111111 "
b00000000 #
b01111111 $
b00000000 %
0&
b00000000000000000000000000110000 (
b0000000011111110 2
b0000000000000000 3
b001111111 4
b000000000 5
b001111111 6
b000000000 7
b011111110 8
b000000000 9
#17000
b10000000 "
b10000000 $
b00000000000000000000000000110011 (
b1111111100000000 2
b110000000 4
b110000000 6
b100000000 8
#18000
b01111111 "
1&
b00000000000000000000000000110110 (
b0000000011111111 2
b001111111 4
b011111111 8
#19000
b01111111 #
b01111111 $
b01111111 %
0&
b00000000000000000000000000111001 (
b0000000011111110 2
b0000000011111110 3
b001111111 5
b001111111 6
b001111111 7
b011111110 8
b011111110 9
#20000
b10000000 $
b10000000 %
1&
b00000000000000000000000000111100 (
b0000000011111111 2
b0000000011111111 3
b110000000 6
b110000000 7
b011111111 8
b011111111 9
#21000
b00000010 "
b00000011 #
b00000100 $
b00000101 %
0&
b00000000000000000000000000111111 (
b0000000000000110 2
b0000000000001000 3
b000000010 4
b000000011 5
b000000100 6
b000000101 7
b000000110 8
b000001000 9
#22000
b00000100 "
b00000101 #
b00000010 $
b00000011 %
b00000000000000000000000001000010 (
b000000100 4
b000000101 5
b000000010 6
b000000011 7
#23000
b10010010 "
b01010111 #
b01111111 $
b11110010 %
b00000000000000000000000001000101 (
b1111111111111111111111111111111111111111111111111111111110010010 *
b0000000000000000000000000000000000000000000000000000000001010111 ,
b0000000000000000000000000000000000000000000000000000000001111111 .
b1111111111111111111111111111111111111111111111111111111111110010 0
b0000000000010001 2
b0000000001001001 3
b110010010 4
b001010111 5
b001111111 6
b111110010 7
b000010001 8
b001001001 9
#24000
1&
b00000000000000000000000001001000 (
b1111111100010011 2
b0000000001100101 3
b100010011 8
b001100101 9
#25000
b01101110 "
b10010001 #
b11001011 $
b00000111 %
0&
b00000000000000000000000001001011 (
b00000000000000000000000000000001 )
b0000000000000000000000000000000000000000000000000000000001101110 *
b1111111111111111111111111111111111111111111111111111111110010001 ,
b1111111111111111111111111111111111111111111111111111111111001011 .
b0000000000000000000000000000000000000000000000000000000000000111 0
b0000000000111001 2
b1111111110011000 3
b001101110 4
b110010001 5
b111001011 6
b000000111 7
b000111001 8
b110011000 9
#26000
1&
b00000000000000000000000001001110 (
b0000000010100011 2
b1111111110001010 3
b010100011 8
b110001010 9
#27000
b10010101 "
b01011000 #
b01111110 $
b11001001 %
0&
b00000000000000000000000001010001 (
b00000000000000000000000000000010 )
b1111111111111111111111111111111111111111111111111111111110010101 *
b0000000000000000000000000000000000000000000000000000000001011000 ,
b0000000000000000000000000000000000000000000000000000000001111110 .
b1111111111111111111111111111111111111111111111111111111111001001 0
b0000000000010011 2
b0000000000100001 3
b110010101 4
b001011000 5
b001111110 6
b111001001 7
b000010011 8
b000100001 9
#28000
1&
b00000000000000000000000001010100 (
b1111111100010111 2
b0000000010001111 3
b100010111 8
b010001111 9
#29000
b00000101 "
b11110000 #
b00011011 $
b11001010 %
0&
b00000000000000000000000001010111 (
b00000000000000000000000000000011 )
b0000000000000000000000000000000000000000000000000000000000000101 *
b1111111111111111111111111111111111111111111111111111111111110000 ,
b0000000000000000000000000000000000000000000000000000000000011011 .
b1111111111111111111111111111111111111111111111111111111111001010 0
b0000000000100000 2
b1111111110111010 3
b000000101 4
b111110000 5
b000011011 6
b111001010 7
b000100000 8
b110111010 9
#30000
1&
b00000000000000000000000001011010 (
b1111111111101010 2
b0000000000100110 3
b111101010 8
b000100110 9
#31000
b01110100 "
b10001111 #
b00011101 $
b10111011 %
0&
b00000000000000000000000001011101 (
b00000000000000000000000000000100 )
b0000000000000000000000000000000000000000000000000000000001110100 *
b1111111111111111111111111111111111111111111111111111111110001111 ,
b0000000000000000000000000000000000000000000000000000000000011101 .
b1111111111111111111111111111111111111111111111111111111110111011 0
b0000000010010001 2
b1111111101001010 3
b001110100 4
b110001111 5
b000011101 6
b110111011 7
b010010001 8
b101001010 9
#32000
1&
b00000000000000000000000001100000 (
b0000000001010111 2
b1111111111010100 3
b001010111 8
b111010100 9
#33000
b01111001 "
b01101111 #
b11001011 $
b00101001 %
0&
b00000000000000000000000001100011 (
b00000000000000000000000000000101 )
b0000000000000000000000000000000000000000000000000000000001111001 *
b0000000000000000000000000000000000000000000000000000000001101111 ,
b1111111111111111111111111111111111111111111111111111111111001011 .
b0000000000000000000000000000000000000000000000000000000000101001 0
b0000000001000100 2
b0000000010011000 3
b001111001 4
b001101111 5
b111001011 6
b000101001 7
b001000100 8
b010011000 9
#34000
1&
b00000000000000000000000001100110 (
b0000000010101110 2
b0000000001000110 3
b010101110 8
b001000110 9
#35000
b01100100 "
b01011011 #
b10001100 $
b11101011 %
0&
b00000000000000000000000001101001 (
b00000000000000000000000000000110 )
b0000000000000000000000000000000000000000000000000000000001100100 *
b0000000000000000000000000000000000000000000000000000000001011011 ,
b1111111111111111111111111111111111111111111111111111111110001100 .
b1111111111111111111111111111111111111111111111111111111111101011 0
b1111111111110000 2
b001100100 4
b001011011 5
b110001100 6
b111101011 7
b111110000 8
#36000
1&
b00000000000000000000000001101100 (
b0000000011011000 2
b0000000001110000 3
b011011000 8
b001110000 9
#37000
b00000011 "
b00001001 #
b00100011 $
b10111011 %
0&
b00000000000000000000000001101111 (
b00000000000000000000000000000111 )
b0000000000000000000000000000000000000000000000000000000000000011 *
b0000000000000000000000000000000000000000000000000000000000001001 ,
b0000000000000000000000000000000000000000000000000000000000100011 .
b1111111111111111111111111111111111111111111111111111111110111011 0
b0000000000100110 2
b1111111111000100 3
b000000011 4
b000001001 5
b000100011 6
b110111011 7
b000100110 8
b111000100 9
#38000
1&
b00000000000000000000000001110010 (
b1111111111100000 2
b0000000001001110 3
b111100000 8
b001001110 9
#39000
b11100011 "
b10010001 #
b01011101 $
b00011011 %
0&
b00000000000000000000000001110101 (
b00000000000000000000000000001000 )
b1111111111111111111111111111111111111111111111111111111111100011 *
b1111111111111111111111111111111111111111111111111111111110010001 ,
b0000000000000000000000000000000000000000000000000000000001011101 .
b0000000000000000000000000000000000000000000000000000000000011011 0
b0000000001000000 2
b1111111110101100 3
b111100011 4
b110010001 5
b001011101 6
b000011011 7
b001000000 8
b110101100 9
#40000
1&
b00000000000000000000000001111000 (
b1111111110000110 2
b1111111101110110 3
b110000110 8
b101110110 9
#41000
b00011110 "
b00010010 #
b01000010 $
b11000101 %
0&
b00000000000000000000000001111011 (
b00000000000000000000000000001001 )
b0000000000000000000000000000000000000000000000000000000000011110 *
b0000000000000000000000000000000000000000000000000000000000010010 ,
b0000000000000000000000000000000000000000000000000000000001000010 .
b1111111111111111111111111111111111111111111111111111111111000101 0
b0000000001100000 2
b1111111111010111 3
b000011110 4
b000010010 5
b001000010 6
b111000101 7
b001100000 8
b111010111 9
#42000
1&
b00000000000000000000000001111110 (
b1111111111011100 2
b0000000001001101 3
b111011100 8
b001001101 9
#43000
b00101010 "
b10110100 #
b10010100 $
b00011110 %
0&
b00000000000000000000000010000001 (
b00000000000000000000000000001010 )
b0000000000000000000000000000000000000000000000000000000000101010 *
b1111111111111111111111111111111111111111111111111111111110110100 ,
b1111111111111111111111111111111111111111111111111111111110010100 .
b0000000000000000000000000000000000000000000000000000000000011110 0
b1111111110111110 2
b1111111111010010 3
b000101010 4
b110110100 5
b110010100 6
b000011110 7
b110111110 8
b111010010 9
#44000
1&
b00000000000000000000000010000100 (
b0000000010010110 2
b1111111110010110 3
b010010110 8
b110010110 9
#45000
b01001100 "
b00110010 #
b01110101 $
b11101100 %
0&
b00000000000000000000000010000111 (
b00000000000000000000000000001011 )
b0000000000000000000000000000000000000000000000000000000001001100 *
b0000000000000000000000000000000000000000000000000000000000110010 ,
b0000000000000000000000000000000000000000000000000000000001110101 .
b1111111111111111111111111111111111111111111111111111111111101100 0
b0000000011000001 2
b0000000000011110 3
b001001100 4
b000110010 5
b001110101 6
b111101100 7
b011000001 8
b000011110 9
#46000
1&
b00000000000000000000000010001010 (
b1111111111010111 2
b0000000001000110 3
b111010111 8
b001000110 9
#47000
b00011010 "
b01001111 #
b10100100 $
b11101000 %
0&
b00000000000000000000000010001101 (
b00000000000000000000000000001100 )
b0000000000000000000000000000000000000000000000000000000000011010 *
b0000000000000000000000000000000000000000000000000000000001001111 ,
b1111111111111111111111111111111111111111111111111111111110100100 .
b1111111111111111111111111111111111111111111111111111111111101000 0
b1111111110111110 2
b0000000000110111 3
b000011010 4
b001001111 5
b110100100 6
b111101000 7
b110111110 8
b000110111 9
#48000
1&
b00000000000000000000000010010000 (
b0000000001110110 2
b0000000001100111 3
b001110110 8
b001100111 9
#49000
b10011110 "
b00010101 #
b11010101 $
b11100101 %
0&
b00000000000000000000000010010011 (
b00000000000000000000000000001101 )
b1111111111111111111111111111111111111111111111111111111110011110 *
b0000000000000000000000000000000000000000000000000000000000010101 ,
b1111111111111111111111111111111111111111111111111111111111010101 .
b1111111111111111111111111111111111111111111111111111111111100101 0
b1111111101110011 2
b1111111111111010 3
b110011110 4
b000010101 5
b111010101 6
b111100101 7
b101110011 8
b111111010 9
#50000
1&
b00000000000000000000000010010110 (
b1111111111001001 2
b0000000000110000 3
b111001001 8
b000110000 9
#51000
b00000000 "
b00110001 #
b11010111 $
b00001010 %
0&
b00000000000000000000000010011001 (
b00000000000000000000000000001110 )
b0000000000000000000000000000000000000000000000000000000000000000 *
b0000000000000000000000000000000000000000000000000000000000110001 ,
b1111111111111111111111111111111111111111111111111111111111010111 .
b0000000000000000000000000000000000000000000000000000000000001010 0
b1111111111010111 2
b0000000000111011 3
b000000000 4
b000110001 5
b111010111 6
b000001010 7
b111010111 8
b000111011 9
#52000
1&
b00000000000000000000000010011100 (
b0000000000101001 2
b0000000000100111 3
b000101001 8
b000100111 9
#53000
b00000101 "
b11001000 #
b10000011 $
b00000011 %
0&
b00000000000000000000000010011111 (
b00000000000000000000000000001111 )
b0000000000000000000000000000000000000000000000000000000000000101 *
b1111111111111111111111111111111111111111111111111111111111001000 ,
b1111111111111111111111111111111111111111111111111111111110000011 .
b0000000000000000000000000000000000000000000000000000000000000011 0
b1111111110001000 2
b1111111111001011 3
b000000101 4
b111001000 5
b110000011 6
b000000011 7
b110001000 8
b111001011 9
#54000
1&
b00000000000000000000000010100010 (
b0000000010000010 2
b1111111111000101 3
b010000010 8
b111000101 9
#55000
b01010000 "
b01010000 #
b00110000 $
b00101010 %
0&
b00000000000000000000000010100101 (
b00000000000000000000000000010000 )
b0000000000000000000000000000000000000000000000000000000001010000 *
b0000000000000000000000000000000000000000000000000000000001010000 ,
b0000000000000000000000000000000000000000000000000000000000110000 .
b0000000000000000000000000000000000000000000000000000000000101010 0
b0000000010000000 2
b0000000001111010 3
b001010000 4
b001010000 5
b000110000 6
b000101010 7
b010000000 8
b001111010 9
#56000
1&
b00000000000000000000000010101000 (
b0000000000100000 2
b0000000000100110 3
b000100000 8
b000100110 9
#57000
b01011100 "
b01010100 #
b01001111 $
b11001010 %
0&
b00000000000000000000000010101011 (
b00000000000000000000000000010001 )
b0000000000000000000000000000000000000000000000000000000001011100 *
b0000000000000000000000000000000000000000000000000000000001010100 ,
b0000000000000000000000000000000000000000000000000000000001001111 .
b1111111111111111111111111111111111111111111111111111111111001010 0
b0000000010101011 2
b0000000000011110 3
b001011100 4
b001010100 5
b001001111 6
b111001010 7
b010101011 8
b000011110 9
#58000
1&
b00000000000000000000000010101110 (
b0000000000001101 2
b0000000010001010 3
b000001101 8
b010001010 9
#59000
b00101011 "
b01000010 #
b01001100 $
b00110010 %
0&
b00000000000000000000000010110001 (
b00000000000000000000000000010010 )
b0000000000000000000000000000000000000000000000000000000000101011 *
b0000000000000000000000000000000000000000000000000000000001000010 ,
b0000000000000000000000000000000000000000000000000000000001001100 .
b0000000000000000000000000000000000000000000000000000000000110010 0
b0000000001110111 2
b0000000001110100 3
b000101011 4
b001000010 5
b001001100 6
b000110010 7
b001110111 8
b001110100 9
#60000
1&
b00000000000000000000000010110100 (
b1111111111011111 2
b0000000000010000 3
b111011111 8
b000010000 9
#61000
b11110110 "
b01101100 #
b10011101 $
b00100010 %
0&
b00000000000000000000000010110111 (
b00000000000000000000000000010011 )
b1111111111111111111111111111111111111111111111111111111111110110 *
b0000000000000000000000000000000000000000000000000000000001101100 ,
b1111111111111111111111111111111111111111111111111111111110011101 .
b0000000000000000000000000000000000000000000000000000000000100010 0
b1111111110010011 2
b0000000010001110 3
b111110110 4
b001101100 5
b110011101 6
b000100010 7
b110010011 8
b010001110 9
#62000
1&
b00000000000000000000000010111010 (
b0000000001011001 2
b0000000001001010 3
b001011001 8
b001001010 9
#63000
b10011100 "
b01100101 #
b10011010 $
b00011111 %
0&
b00000000000000000000000010111101 (
b00000000000000000000000000010100 )
b1111111111111111111111111111111111111111111111111111111110011100 *
b0000000000000000000000000000000000000000000000000000000001100101 ,
b1111111111111111111111111111111111111111111111111111111110011010 .
b0000000000000000000000000000000000000000000000000000000000011111 0
b1111111100110110 2
b0000000010000100 3
b110011100 4
b001100101 5
b110011010 6
b000011111 7
b100110110 8
b010000100 9
#64000
1&
b00000000000000000000000011000000 (
b0000000000000010 2
b0000000001000110 3
b000000010 8
b001000110 9
